Workbook

Sheet Summary
C2: Project | E2: Spreadsmart
C3: Project Manager | E3: ManishkumarNanjibhai Buhecha
C4: Test Team Members | E4: Neha Bharti, Aswini, Anit, Archana
C7: Test Case Summary
C8: Test Case Count | D8: =SUM(D10:D14)
C9: Total Executed Test Cases | E9: Executed Tests | F9: Total Tests
C10: Passed | D10: =SUM(E18:E45) | E10: =IF(D10=0,,(D10/(D10+D11))) | F10: =IF(D9=0,,(D10/D9))
C11: Failed | D11: =SUM(F18:F45) | E11: =IF(D11=0,,(D11/(D10+D11))) | F11: =IF(D9=0,,(D11/D9))
C12: Blocked | D12: =SUM(G18:G45) | E12: 0 | F12: 0
C13: Pending | D13: =SUM(H18:H45) | E13: 0 | F13: 0
C14: Not Applicable | D14: =SUM(I18:I45) | E14: 0 | F14: 0
C16: Feature-wise Test Case Result
C17: Feature Name | D17: Total test cases | E17: PASS | F17: FAIL | G17: Blocked | H17: Pending | I17: NA
C18: SSO Login | D18: ='SSO Login'!D3 | E18: ='SSO Login'!D4 | F18: ='SSO Login'!D5 | G18: ='SSO Login'!D6 | H18: ='SSO Login'!D7 | I18: ='SSO Login'!D8
C19: Login Screen | D19: =SUM('Login Screen'!D3) | E19: =SUM('Login Screen'!D4) | F19: =SUM('Login Screen'!D5) | G19: =SUM('Login Screen'!D6) | H19: =SUM('Login Screen'!D7) | I19: =SUM('Login Screen'!D8)
C20: Security Test | D20: ='Security Test'!D4 | E20: ='Security Test'!D5 | F20: ='Security Test'!D6 | G20: ='Security Test'!D7 | H20: ='Security Test'!D8 | I20: ='Security Test'!D9
C21: Dashboard | D21: =SUM(Dashboard!D3) | E21: =SUM(Dashboard!D4) | F21: =SUM(Dashboard!D5) | G21: =SUM(Dashboard!D6) | H21: =SUM(Dashboard!D7) | I21: =SUM(Dashboard!D8)
C22: Customer Screen | D22: =SUM('Customer Screen'!D3) | E22: =SUM('Customer Screen'!D4) | F22: =SUM('Customer Screen'!D5) | G22: =SUM('Customer Screen'!D6) | H22: =SUM('Customer Screen'!D7) | I22: =SUM('Customer Screen'!D8)
C23: Item Creation | D23: =SUM('Item Creation'!D3) | E23: =SUM('Item Creation'!D4) | F23: =SUM('Item Creation'!D5) | G23: =SUM('Item Creation'!D6) | H23: =SUM('Item Creation'!D7) | I23: =SUM('Item Creation'!D8)
C24: Spreading Screen_Pdf | D24: =SUM('Spreading Screen_Pdf File'!C3) | E24: =SUM('Spreading Screen_Pdf File'!C4) | F24: =SUM('Spreading Screen_Pdf File'!C5) | G24: =SUM('Spreading Screen_Pdf File'!C6) | H24: =SUM('Spreading Screen_Pdf File'!C7) | I24: =SUM('Spreading Screen_Pdf File'!C8)
C25: Spreading Screen_Excel file | D25: =SUM('Spreading Screen_Excel File'!D3) | E25: =SUM('Spreading Screen_Excel File'!D4) | F25: =SUM('Spreading Screen_Excel File'!D5) | G25: =SUM('Spreading Screen_Excel File'!D6) | H25: =SUM('Spreading Screen_Excel File'!D7) | I25: =SUM('Spreading Screen_Excel File'!D8)
C26: Expressions | D26: ='Expressions Verification'!D3 | E26: ='Expressions Verification'!D4 | F26: ='Expressions Verification'!D5 | G26: ='Expressions Verification'!D6 | H26: ='Expressions Verification'!D7 | I26: ='Expressions Verification'!D8
C27: Statement Export | D27: ='Statement Export'!D3 | E27: ='Statement Export'!D4 | F27: ='Statement Export'!D5 | G27: ='Statement Export'!D6 | H27: ='Statement Export'!D7 | I27: ='Statement Export'!D8
C28: Model Management | D28: =SUM('Model Management'!D3) | E28: =SUM('Model Management'!D4) | F28: =SUM('Model Management'!D5) | G28: =SUM('Model Management'!D6) | H28: =SUM('Model Management'!D7) | I28: =SUM('Model Management'!D8)
C29: Clean Pdf | D29: ='Clean PDF'!D3 | E29: ='Clean PDF'!D4 | F29: ='Clean PDF'!D5 | G29: ='Clean PDF'!D6 | H29: ='Clean PDF'!D7 | I29: ='Clean PDF'!D8
C30: Split Pdf | D30: ='Split Pdf'!D3 | E30: ='Split Pdf'!D4 | F30: ='Split Pdf'!D5 | G30: ='Split Pdf'!D6 | H30: ='Split Pdf'!D7 | I30: ='Split Pdf'!D8
C31: Reporting | D31: =SUM(Reporting!D3) | E31: =SUM(Reporting!D4) | F31: =SUM(Reporting!D5) | G31: =SUM(Reporting!D6) | H31: =SUM(Reporting!D7) | I31: =SUM(Reporting!D8)
C32: Admin Screen | D32: =SUM('Admin Screen'!D3) | E32: =SUM('Admin Screen'!D4) | F32: =SUM('Admin Screen'!D5) | G32: =SUM('Admin Screen'!D6) | H32: =SUM('Admin Screen'!D7) | I32: =SUM('Admin Screen'!D8)
C33: Customer Zone | D33: =SUM('Customer Zone'!D3) | E33: =SUM('Customer Zone'!D4) | F33: =SUM('Customer Zone'!D5) | G33: =SUM('Customer Zone'!D6) | H33: =SUM('Customer Zone'!D7) | I33: =SUM('Customer Zone'!D8)
C34: Currency Conversion | D34: ='Currency Conversion'!D3 | E34: ='Currency Conversion'!D4 | F34: ='Currency Conversion'!D5 | G34: ='Currency Conversion'!D6 | H34: ='Currency Conversion'!D7 | I34: ='Currency Conversion'!D8
C35: AIML Training | D35: =SUM('AIML Training'!D3) | E35: =SUM('AIML Training'!D4) | F35: =SUM('AIML Training'!D5) | G35: =SUM('AIML Training'!D6) | H35: =SUM('AIML Training'!D7) | I35: =SUM('AIML Training'!D8)
C36: Notes Processing | D36: =SUM('Notes Processing'!D3) | E36: =SUM('Notes Processing'!D4) | F36: =SUM('Notes Processing'!D5) | G36: =SUM('Notes Processing'!D6) | H36: =SUM('Notes Processing'!D7) | I36: =SUM('Notes Processing'!D8)
C37: Maker Checker | D37: =SUM('Maker Checker'!D3) | E37: =SUM('Maker Checker'!D4) | F37: =SUM('Maker Checker'!D5) | G37: =SUM('Maker Checker'!D6) | H37: =SUM('Maker Checker'!D7) | I37: =SUM('Maker Checker'!D8)
C38: Taxonomy | D38: =SUM(Taxonomy!D3) | E38: =SUM(Taxonomy!D4) | F38: =SUM(Taxonomy!D5) | G38: =SUM(Taxonomy!D6) | H38: =SUM(Taxonomy!D7) | I38: =SUM(Taxonomy!D8)
C39: Exclusion | D39: =SUM(Exclusion!D3) | E39: =SUM(Exclusion!D4) | F39: =SUM(Exclusion!D5) | G39: =SUM(Exclusion!D6) | H39: =SUM(Exclusion!D7) | I39: =SUM(Exclusion!D8)
C40: Autofill Matrix | D40: ='Autofill Matrix'!D3 | E40: ='Autofill Matrix'!D4 | F40: ='Autofill Matrix'!D5 | G40: ='Autofill Matrix'!D6 | H40: ='Autofill Matrix'!D7 | I40: ='Autofill Matrix'!D8
C41: Document Classification | D41: ='Document Classification'!D4 | E41: ='Document Classification'!D5 | F41: ='Document Classification'!D6 | G41: ='Document Classification'!D7 | H41: ='Document Classification'!D8 | I41: ='Document Classification'!D9
C42: Notes Processing-L2 | D42: ='Notes Processing-L2'!D4 | E42: ='Notes Processing-L2'!D5 | F42: ='Notes Processing-L2'!D6 | G42: ='Notes Processing-L2'!D7 | H42: ='Notes Processing-L2'!D8 | I42: ='Notes Processing-L2'!D9
C43: NAICS | D43: =NAICS!D4 | E43: =NAICS!D5 | F43: =NAICS!D6 | G43: =NAICS!D7 | H43: =NAICS!D8 | I43: =NAICS!D9
C44: Covenant | D44: =#REF! | E44: =#REF! | F44: =#REF! | G44: =#REF! | H44: =#REF! | I44: =#REF!
C45: Complex Scenarios | D45: =SUM('Negative Scenarios'!D3) | E45: =SUM('Negative Scenarios'!D4) | F45: =SUM('Negative Scenarios'!D5) | G45: =SUM('Negative Scenarios'!D6) | H45: =SUM('Negative Scenarios'!D7) | I45: =SUM('Negative Scenarios'!D8)
C48: SpreadSmart Automation
C50: Project | E50: Spreadsmart
C51: Project Manager | E51: ManishkumarNanjibhai Buhecha
C52: Automation Test Team Members | E52: Preeti Kumari, Neha Bharti
C55: Test Case Summary
C56: Test Case Count | D56: =SUM(D58:D62)
C57: Total Executed Test Cases | E57: Executed Tests | F57: Total Tests
C58: Passed | D58: =SUM(E66:E95) | E58: =IF(D58=0,,(D58/(D58+D59))) | F58: =IF(D57=0,,(D58/D57))
C59: Failed | D59: =SUM(F66:F95) | E59: =IF(D59=0,,(D59/(D58+D59))) | F59: =IF(D57=0,,(D59/D57))
C60: Blocked | D60: =SUM(G66:G95) | E60: 0 | F60: 0
C61: Pending | D61: =SUM(H66:H95) | E61: 0 | F61: 0
C62: Not Applicable | D62: =SUM(I66:I95) | E62: 0 | F62: 0
C64: Feature-wise Test Case Result
C65: Feature Name | D65: Total test cases | E65: PASS | F65: FAIL | G65: Blocked | H65: Pending | I65: NA
C66: SSO Login | D66: ='SSO Login'!D3 | E66: ='SSO Login'!G4 | F66: ='SSO Login'!G5 | G66: ='SSO Login'!G6 | H66: ='SSO Login'!G7 | I66: ='SSO Login'!G8
C67: Login Screen | D67: =SUM('Login Screen'!D3) | E67: =SUM('Login Screen'!G4) | F67: =SUM('Login Screen'!G5) | G67: =SUM('Login Screen'!G6) | H67: =SUM('Login Screen'!G7) | I67: =SUM('Login Screen'!G8)
C68: Security Test | D68: ='Security Test'!D4 | E68: ='Security Test'!G5 | F68: ='Security Test'!G6 | G68: ='Security Test'!G7 | H68: ='Security Test'!G8 | I68: ='Security Test'!G9
C69: Dashboard | D69: =SUM(Dashboard!D3) | E69: =SUM(Dashboard!G4) | F69: =SUM(Dashboard!G5) | G69: =SUM(Dashboard!G6) | H69: =SUM(Dashboard!G7) | I69: =SUM(Dashboard!G8)
C70: Customer Screen | D70: =SUM('Customer Screen'!D3) | E70: =SUM('Customer Screen'!G4) | F70: =SUM('Customer Screen'!G5) | G70: =SUM('Customer Screen'!G6) | H70: =SUM('Customer Screen'!G7) | I70: =SUM('Customer Screen'!G8)
C71: Item Creation | D71: =SUM('Item Creation'!D3) | E71: =SUM('Item Creation'!G4) | F71: =SUM('Item Creation'!G5) | G71: =SUM('Item Creation'!G6) | H71: =SUM('Item Creation'!G7) | I71: =SUM('Item Creation'!G8)
C72: Spreading Screen_Pdf | D72: =SUM('Spreading Screen_Pdf File'!C3) | E72: =SUM('Spreading Screen_Pdf File'!F4) | F72: =SUM('Spreading Screen_Pdf File'!F5) | G72: =SUM('Spreading Screen_Pdf File'!F6) | H72: =SUM('Spreading Screen_Pdf File'!F7) | I72: =SUM('Spreading Screen_Pdf File'!F8)
C73: Spreading Screen_Excel file | D73: =SUM('Spreading Screen_Excel File'!D3) | E73: =SUM('Spreading Screen_Excel File'!G4) | F73: =SUM('Spreading Screen_Excel File'!G5) | G73: =SUM('Spreading Screen_Excel File'!G6) | H73: =SUM('Spreading Screen_Excel File'!G7) | I73: =SUM('Spreading Screen_Excel File'!D3)
C74: Expressions | D74: ='Expressions Verification'!D3 | E74: ='Expressions Verification'!G4 | F74: ='Expressions Verification'!G5 | G74: ='Expressions Verification'!G6 | H74: ='Expressions Verification'!G7 | I74: ='Expressions Verification'!G8
C75: Statement Export | D75: ='Statement Export'!D3 | E75: ='Statement Export'!G4 | F75: ='Statement Export'!G5 | G75: ='Statement Export'!G6 | H75: ='Statement Export'!G7 | I75: ='Statement Export'!G8
C76: Model Management | D76: =SUM('Model Management'!D3) | E76: =SUM('Model Management'!G4) | F76: =SUM('Model Management'!G5) | G76: =SUM('Model Management'!G6) | H76: =SUM('Model Management'!G7) | I76: =SUM('Model Management'!G8)
C77: Clean Pdf | D77: ='Clean PDF'!D3 | E77: ='Clean PDF'!G4 | F77: ='Clean PDF'!G5 | G77: ='Clean PDF'!G6 | H77: ='Clean PDF'!G7 | I77: ='Clean PDF'!G8
C78: Split Pdf | D78: ='Split Pdf'!D3 | E78: ='Split Pdf'!G4 | F78: ='Split Pdf'!G5 | G78: ='Split Pdf'!G6 | H78: ='Split Pdf'!G7 | I78: ='Split Pdf'!G8
C79: Bulk Upload | D79: =' Bulk Upload'!D3 | E79: =' Bulk Upload'!G4 | F79: =' Bulk Upload'!G5 | G79: =' Bulk Upload'!G6 | H79: =' Bulk Upload'!G7 | I79: =' Bulk Upload'!G8
C80: Reporting | D80: =SUM(Reporting!D3) | E80: =SUM(Reporting!G4) | F80: =SUM(Reporting!G5) | G80: =SUM(Reporting!G6) | H80: =SUM(Reporting!G7) | I80: =SUM(Reporting!G8)
C81: Admin Screen | D81: =SUM('Admin Screen'!D3) | E81: =SUM('Admin Screen'!G4) | F81: =SUM('Admin Screen'!G5) | G81: =SUM('Admin Screen'!G6) | H81: =SUM('Admin Screen'!G7) | I81: =SUM('Admin Screen'!G8)
C82: Customer Zone | D82: =SUM('Customer Zone'!D3) | E82: =SUM('Customer Zone'!G4) | F82: =SUM('Customer Zone'!G5) | G82: =SUM('Customer Zone'!G6) | H82: =SUM('Customer Zone'!G7) | I82: =SUM('Customer Zone'!G8)
C83: Currency Conversion | D83: ='Currency Conversion'!D3 | E83: ='Currency Conversion'!G4 | F83: ='Currency Conversion'!G5 | G83: ='Currency Conversion'!G6 | H83: ='Currency Conversion'!G7 | I83: ='Currency Conversion'!G8
C84: AIML Training | D84: =SUM('AIML Training'!D3) | E84: =SUM('AIML Training'!G4) | F84: =SUM('AIML Training'!G5) | G84: =SUM('AIML Training'!G6) | H84: =SUM('AIML Training'!G7) | I84: =SUM('AIML Training'!G8)
C85: Notes Processing | D85: =SUM('Notes Processing'!D3) | E85: =SUM('Notes Processing'!G4) | F85: =SUM('Notes Processing'!G5) | G85: =SUM('Notes Processing'!G6) | H85: =SUM('Notes Processing'!G7) | I85: =SUM('Notes Processing'!G8)
C86: Maker Checker | D86: =SUM('Maker Checker'!D3) | E86: =SUM('Maker Checker'!G4) | F86: =SUM('Maker Checker'!G5) | G86: =SUM('Maker Checker'!G6) | H86: =SUM('Maker Checker'!G7) | I86: =SUM('Maker Checker'!G8)
C87: Taxonomy | D87: =SUM(Taxonomy!D3) | E87: =SUM(Taxonomy!G4) | F87: =SUM(Taxonomy!G5) | G87: =SUM(Taxonomy!G6) | H87: =SUM(Taxonomy!G7) | I87: =SUM(Taxonomy!G8)
C88: Exclusion | D88: =SUM(Exclusion!D3) | E88: =SUM(Exclusion!G4) | F88: =SUM(Exclusion!G5) | G88: =SUM(Exclusion!G6) | H88: =SUM(Exclusion!G7) | I88: =SUM(Exclusion!G8)
C89: Autofill Matrix | D89: ='Autofill Matrix'!D3 | E89: ='Autofill Matrix'!G4 | F89: ='Autofill Matrix'!G5 | G89: ='Autofill Matrix'!G6 | H89: ='Autofill Matrix'!G7 | I89: ='Autofill Matrix'!G8
C90: Document Classification | D90: ='Document Classification'!D4 | E90: ='Document Classification'!G5 | F90: ='Document Classification'!G6 | G90: ='Document Classification'!G7 | H90: ='Document Classification'!G8 | I90: ='Document Classification'!G9
C91: Notes Processing-L2 | D91: ='Notes Processing-L2'!D4 | E91: ='Notes Processing-L2'!G5 | F91: ='Notes Processing-L2'!G6 | G91: ='Notes Processing-L2'!G7 | H91: ='Notes Processing-L2'!G8 | I91: ='Notes Processing-L2'!G9
C92: NAICS | D92: =NAICS!D4 | E92: =NAICS!G5 | F92: =NAICS!G6 | G92: =NAICS!G7 | H92: =NAICS!G8 | I92: =NAICS!G9
C93: Covenant | D93: =#REF! | E93: =#REF! | F93: =#REF! | G93: =#REF! | H93: =#REF! | I93: =#REF!
C94: Complex Scenarios | D94: =SUM('Negative Scenarios'!D3) | E94: =SUM('Negative Scenarios'!G4) | F94: =SUM('Negative Scenarios'!G5) | G94: =SUM('Negative Scenarios'!G6) | H94: =SUM('Negative Scenarios'!G7) | I94: =SUM('Negative Scenarios'!G8)
C95: Global To Child | D95: =SUM('Global To Child'!D3) | E95: =SUM('Global To Child'!G4) | F95: =SUM('Global To Child'!G5) | G95: =SUM('Global To Child'!G6) | H95: =SUM('Global To Child'!G7) | I95: =SUM('Global To Child'!G8)

Sheet SSO Login
B2: Test Case Summary
B3: Total Test Cases | D3: =SUM(D4:D8) | E3: Executed Tests | F3: Total Tests | G3: Automation Scripts
B4: Passed | D4: =COUNTIF(F9:F34,"Passed") | E4: =IF(D4=0,,(D4/(D4+D5))) | F4: =IF(D3=0,,(D4/D3)) | G4: =COUNTIF(H10:H493,"Done")
B5: Failed | D5: =COUNTIF(F9:F139,"Failed") | E5: =IF(D5=0,,(D5/(D5+D6))) | F5: =IF(D3=0,,(D5/D3)) | G5: =COUNTIF(H10:H493,"Failed")
B6: Blocked | D6: =COUNTIF(F9:F139,"Blocked") | E6: =IF(D6=0,,(D6/(D6+D7))) | F6: =IF(D3=0,,(D6/D3)) | G6: =COUNTIF(H10:H493,"Blocked")
B7: Pending | D7: =COUNTIF(F9:F139,"Pending") | E7: =IF(D7=0,,(D7/(D7+D8))) | F7: =IF(D3=0,,(D7/D3)) | G7: =COUNTIF(H10:H493,"Pending")
B8: Not Applicable | D8: =COUNTIF(F10:F139,"NA") | E8: =IF(D8=0,,(D8/(D8+D9))) | F8: =IF(D3=0,,(D8/D3)) | G8: =COUNTIF(H10:H493,"Out of Scope")
B9: S.No. | C9: Module/Sub-Module | D9: Test Steps | E9: Expected Results | F9: Result | G9: Bug ID | H9: Automation Status | I9: Mapped Scripts | J9: Comments
B10: SSOLogin_001 | C10: Login Page | D10: Open the Spreadsmart URL as a registered user and verify that the sign-in page is displayed with Email and Password fields. | E10: The sign-in page should be displayed, and the user should be able to proceed with valid credentials. | F10: NA | H10: Out of Scope
B11: SSOLogin_002 | C11: Login - New User | D11: Click the "Login with SSO" button on the login page. | E11: The button should be clickable. | F11: NA | H11: Out of Scope
B12: SSOLogin_003 | C12: Login - Existing User | D12: Sign in with valid credentials for an existing user. | E12: The user should be able to navigate to the page available for the assigned role. | F12: NA | H12: Out of Scope
B13: SSOLogin_004 | C13: Login - Invalid User | D13: Attempt to sign in with invalid user credentials and observe the validation message. | E13: A validation message should be displayed indicating that the username or password is invalid. | F13: NA | H13: Out of Scope
B14: SSOLogin_005 | C14: Login - Rejected User | D14: Attempt to sign in with a rejected user account and verify the validation message. | E14: The user should not be able to sign in and should receive the message "Your account has not been approved." | F14: NA | H14: Out of Scope
B15: SSOLogin_006 | C15: Login - Inactive User | D15: Attempt to sign in with an inactive user account and verify the validation message. | E15: The user should not be able to sign in and should receive the message "Your account has not been approved." | F15: NA | H15: Out of Scope
B16: SSOLogin_007 | C16: Login - Incorrect Password | D16: Attempt to sign in with an incorrect password and observe the response. | E16: A validation message should be displayed during sign-in. | F16: NA | H16: Out of Scope
B17: SSOLogin_008 | C17: Login - Invalid Domain | D17: Attempt to register with an unsupported email domain. | E17: A message should be displayed indicating that email IDs from this domain are not supported. | F17: NA | G17: Message is different | H17: Out of Scope
B18: SSOLogin_009 | C18: Login - Cross Browser | D18: Verify the login flow in different browsers (Chrome and Microsoft Edge). | E18: Login should work in all supported browsers. | F18: NA | H18: Out of Scope
B19: SSOLogin_010 | C19: Login - Close Tab | D19: Close the Spreadsmart window, then reopen the login URL. | E19: The user should be able to navigate to the page available for the assigned role. | F19: NA | H19: Out of Scope
B20: SSOLogin_011 | C20: Duplicate Tab | D20: Duplicate an already opened application tab and observe the new tab. | E20: The Spreadsmart application should open in the duplicated tab with the same user session. | F20: NA | H20: Out of Scope
B21: SSOLogin_012 | C21: Copy URL | D21: Sign in to the application, copy the URL, and paste it into a second tab. | E21: The sign-in page should be displayed to the user. | F21: NA | H21: Out of Scope
B22: SSOLogin_013 | C22: Login - Admin | D22: Sign in with a user who has the Admin role and verify the landing screen. | E22: The user should be able to sign in and view all options available to the Admin role. | F22: NA | H22: Out of Scope
B23: SSOLogin_014 | C23: Login - Analyst | D23: Sign in with a user who has the Analyst role and verify the landing screen. | E23: The user should be able to sign in and view all options available to the Analyst role. | F23: NA | H23: Out of Scope
B24: SSOLogin_015 | C24: Login - Global Manager | D24: Sign in with a user who has the Global Manager role and verify the landing screen. | E24: The user should be able to sign in and view all options available to the Global Manager role. | F24: NA | H24: Out of Scope
B25: SSOLogin_016 | C25: Login - Manager | D25: Sign in with a user who has the Manager role and verify the landing screen. | E25: The user should be able to sign in and view all options available to the Manager role. | F25: NA | H25: Out of Scope
B26: SSOLogin_017 | C26: Logout Button | D26: After signing in to Spreadsmart, click the Logout button. | E26: The user should be logged out and redirected to the sign-in page. | F26: NA | H26: Out of Scope
B27: SSOLogin_018 | C27: Logout Page | D27: After logout, verify that the user must enter credentials again to sign in. | E27: The sign-in page should be displayed, and the user should be prompted to enter credentials again. | F27: NA | H27: Out of Scope
B28: SSOLogin_019 | C28: Logout - Admin | D28: Sign in with an Admin user, then click the Logout button and observe the behavior. | E28: The Admin user should be able to log out successfully. | F28: NA | H28: Out of Scope
B29: SSOLogin_020 | C29: Logout - Analyst | D29: Sign in with an Analyst user, then click the Logout button and observe the behavior. | E29: The Analyst user should be able to log out successfully. | F29: NA | H29: Out of Scope
... B35: SSOLogin_026 | C35: Logout - Cross Browser | D35: Verify the logout flow in different browsers (Chrome and Microsoft Edge). | E35: Logout and sign-in should work in all supported browsers. | F35: NA | H35: Out of Scope
B36: SSOLogin_027 | C36: Login Page | D36: Verify the behavior when the screen becomes blank during SSO login. | E36: Login should complete successfully. | F36: NA | G36: 136306 | H36: Out of Scope | J36: [Needs QA Review: original wording ambiguous]

Sheet Login Screen
B2: Test Case Summary
B3: Total Test Cases | D3: =SUM(D4:D8) | E3: Executed Tests | F3: Total Tests | G3: Automation Scripts
B4: Passed | D4: =COUNTIF(F10:F98,"Passed") | E4: =IF(D4=0,,(D4/(D4+D5))) | F4: =IF(D3=0,,(D4/D3)) | G4: =COUNTIF(H10:H493,"Done")
B5: Failed | D5: =COUNTIF(F10:F98,"Failed") | E5: =IF(D5=0,,(D5/(D5+D6))) | F5: =IF(D3=0,,(D5/D3)) | G5: =COUNTIF(H10:H493,"Failed")
B6: Blocked | D6: =COUNTIF(F10:F98,"Blocked") | E6: =IF(D6=0,,(D6/(D6+D7))) | F6: =IF(D3=0,,(D6/D3)) | G6: =COUNTIF(H10:H493,"Blocked")
B7: Pending | D7: =COUNTIF(F10:F98,"Pending") | E7: =IF(D7=0,,(D7/(D7+D8))) | F7: =IF(D3=0,,(D7/D3)) | G7: =COUNTIF(H10:H493,"Pending")
B8: Not Applicable | D8: =COUNTIF(F10:F98,"NA") | E8: =IF(D8=0,,(D8/(D8+D9))) | F8: =IF(D3=0,,(D8/D3)) | G8: =COUNTIF(H10:H493,"Out of Scope")
B9: S.No. | C9: Module/Sub-Module | D9: Test Steps | E9: Expected Results | F9: Result | G9: Bug ID | H9: Automation Status | I9: Mapped Scripts | J9: Comments
B10: Login_001 | C10: Register Screen | D10: Click the "Register here" link on the login page. | E10: The Register Now page should open, and the cursor should be placed in the First Name field. | F10: Passed | H10: Pending | J10: 0.25
B11: Login_002 | C11: Register Screen | D11: Enter alphabetic, numeric, and alphanumeric values in the First Name and Last Name fields. | E11: The entered values should be displayed in the fields. | F11: Passed | H11: Pending | J11: 0.25
B12: Login_003 | C12: Register Screen | D12: Enter an email ID in the required format. | E12: A valid email ID format should be accepted. | F12: Passed | H12: Pending | J12: 0.25
B13: Login_004 | C13: Register Screen | D13: Enter a Windows user ID in the User ID field. | E13: The user should be able to enter the User ID. | F13: Passed | H13: Pending | J13: 0.25
B14: Login_005 | C14: Register Screen | D14: Enter a password with at least 8 characters, including one special character, one uppercase letter, one lowercase letter, and one number. Then enter the same value in the Confirm Password field. | E14: The password should meet the validation rules, and the values entered in the Password and Confirm Password fields should be masked. | F14: Passed | H14: Pending | J14: 0.5
B15: Login_006 | C15: Register Screen | D15: Click the "Register Now" button. | E15: A "User Registered Successfully" pop-up should be displayed. | F15: Passed | H15: Pending | J15: 0.25
B16: Login_007 | C16: Login Screen | D16: After the user is approved, click the "Windows Login" button to proceed. | E16: Windows login should work for an approved user. | F16: Passed | H16: Out of Scope
B17: Login_008 | C17: Login Screen | D17: 1. Attempt login with the correct user ID and an incorrect password. 2. Attempt login with the correct password and an incorrect user ID. | E17: An "Incorrect password or username" message should be displayed. | F17: Passed | H17: Pending | J17: 0.5
B18: Login_009 | C18: Login Screen | D18: Attempt login with an email ID from an invalid domain. | E18: The system should not accept the unsupported domain. | F18: Passed | H18: Pending | J18: 0.5
B19: Login_010 | C19: Forgot Password | D19: Click "Forgot Password", enter an email ID, verify that the email is received, open the reset link, enter a new password, and log in with the new password. | E19: A reset email should be received, the reset link should work, and the user should be able to log in with the new password. | F19: Passed | H19: Out of Scope | J19: As of now we're not covering Email verification in automation
B20: Login_011 | C20: Forgot Password | D20: Enter an incorrect email ID in the Forgot Password flow. Then verify the behavior when the old password is used in the Reset Password window. | E20: No reset email should be received, and the user should be prompted to set a new password. | F20: Passed | H20: Out of Scope | J20: As of now we're not covering Email verification in automation
B21: Login_012 | C21: Login Screen | D21: Click the Windows Login button and proceed to the Spreadsmart application. | E21: The Dashboard should open. | F21: Passed | H21: Done
B22: Login_013 | C22: Login Screen | D22: Verify the Terms of Use and Privacy Policy links on the login page. | E22: The links should be visible and clickable. | F22: Passed | H22: Pending | J22: 0.5
B23: Login_014 | C23: Login Screen | D23: Attempt to log in with a user who has not yet been approved. | E23: An appropriate validation message should be displayed. | F23: Passed | G23: 136312 | H23: Pending

Sheet Security Test
B2: Test Case Summary
B3: Total Test Cases | D3: 1st Iteration | E3: Executed Tests | F3: Total Tests | G3: Automation Scripts
D4: =SUM(D5:D9)
B5: Passed | D5: =COUNTIF(F11:F273,"Passed") | E5: =IF(D5=0,,(D5/(D5+D6))) | F5: =IF(D4=0,,(D5/D4)) | G5: =COUNTIF(H11:H494,"Done")
B6: Failed | D6: =COUNTIF(F11:F273,"Failed") | E6: =IF(D6=0,,(D6/(D6+D7))) | F6: =IF(D4=0,,(D6/D4)) | G6: =COUNTIF(H11:H494,"Failed")
B7: Blocked | D7: =COUNTIF(F11:F273,"Blocked") | E7: =IF(D7=0,,(D7/(D7+D8))) | F7: =IF(D4=0,,(D7/D4)) | G7: =COUNTIF(H11:H494,"Blocked")
B8: Pending | D8: =COUNTIF(F11:F273,"Pending") | E8: =IF(D8=0,,(D8/(D8+D9))) | F8: =IF(D4=0,,(D8/D4)) | G8: =COUNTIF(H11:H494,"Pending")
B9: Not Applicable | D9: =COUNTIF(F11:F273,"Not Applicable") | E9: =IF(D9=0,,(D9/(D9+#REF!))) | F9: =IF(D4=0,,(D9/D4)) | G9: =COUNTIF(H11:H494,"Out of Scope")
B10: S.No. | C10: Module/Sub-Module | D10: Test Steps | E10: Expected Results | F10: Result | G10: Bug ID | H10: Automation Status | I10: Mapped Scripts | J10: Comments
B11: Security_001 | C11: Login Screen | D11: Enter alphabetic, numeric, and alphanumeric values in the First Name and Last Name fields. | E11: The entered values should be displayed in the fields. | F11: Pending | H11: Pending | J11: 0.25
B12: Security_002 | C12: Login Screen | D12: Enter an email ID in the required format. | E12: A valid email ID format should be accepted. | F12: Pending | H12: Pending | J12: 0.25
B13: Security_003 | C13: Login Screen | D13: Enter a Windows user ID in the User ID field. | E13: The user should be able to enter the User ID. | F13: Pending | H13: Pending | J13: 0.25
B14: Security_004 | C14: Login Screen | D14: Enter a password with at least 8 characters, including one special character, one uppercase letter, one lowercase letter, and one number. Then enter the same value in the Confirm Password field. | E14: The password should meet the validation rules, and the values entered in the Password and Confirm Password fields should be masked. | F14: Pending | H14: Pending | J14: 0.25
B15: Security_005 | C15: Login Screen | D15: 1. Attempt login with the correct user ID and an incorrect password. 2. Attempt login with the correct password and an incorrect user ID. | E15: An "Incorrect password or username" message should be displayed. | F15: Pending | H15: Pending | J15: 0.5
B16: Security_006 | C16: Login Screen | D16: Attempt login with an email ID from an invalid domain. | E16: The system should not accept the unsupported domain. | F16: Pending | H16: Pending | J16: 0.5
B17: Security_007 | C17: Login Screen | D17: Enter an incorrect email ID in the Forgot Password flow. Then verify the behavior when the old password is used in the Reset Password window. | E17: No reset email should be received, and the user should be prompted to set a new password. | F17: Pending | H17: Out of Scope
B18: Security_008 | C18: Login Screen | D18: Attempt to copy and paste data into the email and password fields. | E18: The user should not be allowed to paste data into these fields. | F18: Pending | H18: Pending | J18: 0.5
B19: Security_009 | C19: Login Screen | D19: Attempt to log in with an unapproved account. | E19: The user should receive a message stating that the account has not been approved. | F19: Pending | H19: Pending | J19: 1
B20: Security_010 | C20: Group Access | D20: Provide a user with access to limited groups and log in with that user. Then view data in Existing Customers, Models, and Reports. | E20: The user should see data only for the assigned groups. Data for other groups should not be visible. | F20: Pending | H20: Pending | J20: 1
B21: Security_011 | C21: Group Access | D21: Provide a user with access to limited groups and log in with that user. Then go to Statement Export and review the customer and model lists. | E21: Only customers and models linked to the accessible groups should be displayed. | F21: Pending | H21: Pending | J21: 1
B22: Security_012 | C22: Admin | D22: Verify that an Admin user can access the features defined for the role in the role matrix. | E22: The Admin user should have access according to the configured role matrix. | F22: Pending | G22: 70778 | H22: Pending | I22: 2 | J22: ..\Downloads\Roles and Rights Sample.docx
B23: Security_013 | C23: Manager | D23: Verify that a Manager user can access the features defined for the role in the role matrix. | E23: The Manager user should have access according to the configured role matrix. | F23: Pending | H23: Pending | J23: 2
B24: Security_014 | C24: Global Manager | D24: Verify that a Global Manager user can access the features defined for the role in the role matrix. | E24: The Global Manager user should have access according to the configured role matrix. | F24: Pending | H24: Pending | J24: 2
B25: Security_015 | C25: Analyst | D25: Verify that an Analyst user can access the features defined for the role in the role matrix. | E25: The Analyst user should have access according to the configured role matrix. | F25: Pending | H25: Pending | J25: 2
B26: Security_016 | C26: Login Screen | D26: Attempt to log in with an inactive user account. | E26: The user should not be able to log in and should receive the message "Your account has not been approved." | F26: Pending | G26: Newly added | H26: Pending | J26: 1
B27: Security_017 | C27: Login Screen | D27: Attempt to log in with a rejected user account. | E27: The user should not be able to log in and should receive the message "Your account has not been approved." | F27: Pending | G27: Newly added | H27: Pending | J27: 1
B28: Security_018 | C28: Login Screen | D28: Log in to Spreadsmart. While the session is active, have another user reject or deactivate the account. | E28: The current user should be able to continue working until the session expires. | F28: Pending | G28: Newly added | H28: Out of Scope | J28: multiple session in parallel is not supported in cypress
B29: Security_019 | C29: Access Issue | D29: Log in to Spreadsmart. While the session is active, have another user change the access from Admin to Manager or another role. | E29: The current user should be able to continue working until the session expires. | F29: Pending | G29: Newly added | H29: Out of Scope

Sheet Dashboard
B2: Test Case Summary
B3: Total Test Cases | D3: =SUM(D4:D8) | E3: Executed Tests | F3: Total Tests | G3: Automation Scripts
B4: Passed | D4: =COUNTIF(F9:F46,"Passed") | E4: =IF(D4=0,,(D4/(D4+D5))) | F4: =IF(D3=0,,(D4/D3)) | G4: =COUNTIF(H10:H489,"Done")
B5: Failed | D5: =COUNTIF(F9:F46,"Failed") | E5: =IF(D5=0,,(D5/(D5+D6))) | F5: =IF(D3=0,,(D5/D3)) | G5: =COUNTIF(H10:H489,"Failed")
B6: Blocked | D6: =COUNTIF(F9:F46,"Blocked") | E6: =IF(D6=0,,(D6/(D6+D7))) | F6: =IF(D3=0,,(D6/D3)) | G6: =COUNTIF(H10:H489,"Blocked")
B7: Pending | D7: =COUNTIF(F9:F46,"Pending") | E7: =IF(D7=0,,(D7/(D7+D8))) | F7: =IF(D3=0,,(D7/D3)) | G7: =COUNTIF(H10:H489,"Pending")
B8: Not Applicable | D8: =COUNTIF(F9:F46,"Not Applicable") | E8: =IF(D8=0,,(D8/(D8+#REF!))) | F8: =IF(D3=0,,(D8/D3)) | G8: =COUNTIF(H10:H489,"Out of Scope")
B9: S.No. | C9: Module/Sub-Module | D9: Test Steps | E9: Expected Results | F9: Result | G9: Bug ID | H9: Automation Status | I9: Mapped Scripts | J9: Comments
B10: Dash_001 | C10: Dashboard | D10: Log in to Spreadsmart using Analyst or Admin credentials. | E10: The user should be able to log in to the application. | F10: Pending | H10: Done
B11: Dash_002 | C11: Dashboard | D11: Observe the first screen after login. | E11: The Dashboard should be displayed after login. | F11: Pending | H11: Done
B12: Dash_003 | C12: Dashboard | D12: Verify that the Dashboard menu is present on the home screen. | E12: The home screen should display Dashboard, Spreading, Reporting, and Admin sections. | F12: Pending | H12: Done
B13: Dash_004 | C13: Dashboard | D13: Verify that the Dashboard displays the following options: Spreads Overall Projects Project Assignment Status | E13: The listed options should be displayed. | F13: Pending | H13: Done
B14: Dash_005 | C14: Dashboard | D14: Verify that Overall Projects displays a graph for item statuses such as Received, Draft, For QC, Spread, Hold, Rejected, and All. | E14: The graph should be displayed. | F14: Pending | H14: Done
B15: Dash_006 | C15: Dashboard | D15: Verify that the Spreads section displays status tabs such as Received, Draft, For QC, Spread, Hold, Rejected, and All. Then review the customer details shown under each status. | E15: Customer details such as Customer Name, Group, For Spread, and Analyst Name should be displayed. | F15: Pending | H15: Done
B16: Dash_007 | C16: Statement Date Filter | D16: Apply the Statement Date filter and observe the data. | E16: Data should be displayed according to the selected statement date. | F16: Pending | H16: Done
B17: Dash_008 | C17: Group Filter | D17: 1. Apply the Group filter and select a group. Observe the results in the Received, Draft, Hold, Spread, For QC, Rejected, and All tabs. 2. Select a group with no data and review all tabs. | E17: 1. Data should appear according to the selected group. 2. No data should appear in any tab for a group with no data. | F17: Pending | H17: Done
B18: Dash_009 | C18: Graph | D18: Verify the graph after applying different filters: 1. Group filter 2. Statement Date filter | E18: The graph should display data according to the applied filters. | F18: Pending | H18: Done
B19: Dash_010 | C19: Graph | D19: Apply a Statement Date filter for which no data is available. | E19: The graph should display the message "No data available." | F19: Pending | H19: Done
B20: Dash_011 | C20: Group Filter | D20: Log in with a group that has no data available and observe the Dashboard. | E20: The Dashboard should show "No data available" and should not display data for other groups. | F20: Pending | H20: Done
B21: Dash_012 | C21: Dashboard | D21: Verify that Project Assignment Status shows the number of spreads and the average time taken. | E21: The Project Assignment Status graph should be displayed. | F21: Pending | H21: Done
... B25: Dash_016 | C25: Pagination | D25: Precondition: A large number of items should be available. Scroll down the page, click the next page, and then change the number of items from the dropdown. | E25: The user should be navigated to the selected page, and the selected item count should be applied from the dropdown. | F25: Pending | H25: Done
B26: Dash_018 | C26: Tab Switching | D26: Log in to the dashboard URL, then switch to another tab and return to the application tab. Verify the behavior when the reported error occurs after login and after tab switching. | E26: The Dashboard should remain accessible when switching tabs. | F26: Pending | G26: 136550 | H26: Pending | J26: [Needs QA Review: original expected result missing]

Sheet Customer Screen
B2: Test Case Summary
B3: Total Test Cases | D3: =SUM(D4:D8) | E3: Executed Tests | F3: Total Tests | G3: Automation Scripts
B4: Passed | D4: =COUNTIF(F10:F101,"Passed") | E4: =IF(D4=0,,(D4/(D4+D5))) | F4: =IF(D3=0,,(D4/D3)) | G4: =COUNTIF(H10:H494,"Done")
B5: Failed | D5: =COUNTIF(F10:F101,"Failed") | E5: =IF(D5=0,,(D5/(D5+D6))) | F5: =IF(D3=0,,(D5/D3)) | G5: =COUNTIF(H10:H494,"Failed")
B6: Blocked | D6: =COUNTIF(F10:F101,"Blocked") | E6: =IF(D6=0,,(D6/(D6+D7))) | F6: =IF(D3=0,,(D6/D3)) | G6: =COUNTIF(H10:H494,"Blocked")
B7: Pending | D7: =COUNTIF(F10:F101,"Pending") | E7: =IF(D7=0,,(D7/(D7+D8))) | F7: =IF(D3=0,,(D7/D3)) | G7: =COUNTIF(H10:H494,"Pending")
B8: Not Applicable | D8: =COUNTIF(F10:F101,"Not Applicable") | E8: =IF(D8=0,,(D8/(D8+#REF!))) | F8: =IF(D3=0,,(D8/D3)) | G8: =COUNTIF(H10:H494,"Out of Scope")
B9: S.No. | C9: Module/Sub-Module | D9: Test Steps | E9: Expected Results | F9: Result | G9: Bug ID | H9: Automation Status | I9: Mapped Scripts | J9: Comments
B10: Cust_001 | C10: Create Customer | D10: Log in to Spreadsmart, navigate to Create Customer, and review the available options. | E10: The Create Customer page should open. | F10: Pending | H10: Done | I10: automationTestScenario.js
B11: Cust_002 | C11: Create Customer | D11: Verify that the Create Customer screen displays the following fields: Customer Name Customer ID Year End Group Ticker QC Date Range Target Currency Size of Business Comments Submit button | E11: The listed fields should be displayed on the screen. | F11: Pending | H11: Done
B12: Cust_003 | C12: Create Customer | D12: Enter values in the mandatory and optional fields, save the customer, then navigate to the Existing Customer screen and review the created record. | E12: The user should be able to create the customer and view it in the customer list. | F12: Pending | H12: Done | I12: automationTestScenario.js
B13: Cust_004 | C13: Create Customer | D13: Enter a duplicate Customer ID and submit. Then enter a duplicate customer name and submit. | E13: A duplicate Customer ID should not be allowed. A duplicate customer name should be allowed. | F13: Pending | H13: Done
B14: Cust_005 | C14: Existing Customer | D14: Log in to Spreadsmart and navigate to the Existing Customer page from the Spreading menu. | E14: The Existing Customer page should be displayed. | F14: Pending | H14: Done | I14: automationTestScenario.js
B15: Cust_006 | C15: Existing Customer | D15: Open the Existing Customer page and review the displayed columns. | E15: The Existing Customer page should display columns such as Customer Name, Entity Type, Group Name, For Spread, Status, and Actions. | F15: Pending | H15: Done
B16: Cust_007 | C16: Existing Customer | D16: Open the Existing Customer page and click a Customer Name to load the customer information page. Verify that the page shows Customer Name, Customer ID, Year End, Group, Ticker, QC, Date Range, NAICS Suggestions, Target Currency, Size of Business, Comments, and Submit. | E16: All listed fields should be displayed as editable. | F16: Pending | H16: Done
B17: Cust_008 | C17: Customer Information | D17: Ensure all mandatory (*) fields contain valid values, then click Update. | E17: The customer should be updated successfully, and a "Customer successfully updated" message should be displayed. | F17: Pending | H17: Done
B18: Cust_009 | C18: My Favourite | D18: Click the star icon to add a customer to favourites. Then open My Favourite, select the customer, and click Modify. | E18: The user should be navigated to the Modify Customer page, and the page should display the data entered during customer creation. | F18: Pending | H18: Done
B19: Cust_010 | C19: Validate 'Favorite' Functionality | D19: Open the customer listing page and click the favourite (star) icon for a customer. | E19: The star icon should be filled, and the customer should appear under My Favourite. | F19: Pending | H19: Done
B20: Cust_011 | C20: Check Customers Under 'My Favourite' | D20: Verify the My Favourite page when no customer is marked as favourite. | E20: No customer should be displayed on the customer list page. | F20: Pending | H20: Done
B21: Cust_012 | C21: Check Customers Under 'My Favourite' | D21: 1. Mark customers as favourite. 2. Review the My Favourite page. | E21: All customers marked as favourite by the logged-in user should be displayed under My Favourite. | F21: Pending | H21: Done
B22: Cust_013 | C22: Validate 'UnFavorite' Functionality | D22: Open the customer listing page, click the favourite (star) icon for a customer, and then click it again. | E22: The star icon should be cleared, and the customer should be removed from My Favourite. | F22: Pending | H22: Done
B23: Cust_014 | C23: Check Customers Under 'My Favourite' | D23: 1. Mark customers as unfavourite. 2. Review the My Favourite page. | E23: Customers marked as unfavourite by the logged-in user should be removed from My Favourite. | F23: Pending | H23: Done
B24: Cust_015 | C24: Customer Listing | D24: Open My Favourite and click a customer name on the customer listing page. | E24: The page should display the data entered during customer creation. | F24: Pending | H24: Done
B25: Cust_016 | C25: Modify Customer | D25: Click a customer name on the customer listing page, modify the customer metadata, and update the information. | E25: The user should be able to modify the customer data. | F25: Pending | H25: Done
B26: Cust_017 | C26: Modify Customer | D26: Navigate to Existing Customer, open any customer record, select the QC checkbox and date range, then click Update. | E26: The Start Date and End Date should be displayed after the customer is updated. | F26: Pending | H26: Done
... B31: Cust_022 | C31: NAICS | D31: On the Modify Customer screen, review the NAICS suggestion. After selecting a NAICS value, leave mandatory fields blank in the details table and click Update. | E31: Validation errors should be displayed for the mandatory fields, and the update should not be completed. | F31: Pending | H31: Done
B32: Cust_023 | C32: NAICS | D32: Verify the delete functionality for NAICS after adding multiple NAICS entries with different percentages. | E32: NAICS data should be deleted successfully. The total percentage for added NAICS entries should remain 100%. | F32: Pending | H32: Pending | I32: 0.5
B33: Cust_024 | C33: Modify Customer | D33: Modify any customer from Existing Customers, clear mandatory fields, and click Update. | E33: The system should display validation messages for the missing mandatory fields. | F33: Pending | G33: Newly Added | H33: Pending | I33: 0.5 | J33: 44922
B34: Cust_025 | C34: Modify Customer - Additional Information | D34: Review the Additional Information section for Add User and Add Customer Details. | E34: The user should be able to add user and customer details in this section. | F34: Pending | H34: Pending | I34: 0.5
B35: Cust_026 | C35: Modify Customer - Additional Information | D35: Review the Add Customer Details section and verify the mandatory fields. | E35: The user should be able to enter all required fields under Customer Details. | F35: Pending | H35: Pending | I35: 0.25
B36: Cust_027 | C36: Modify Customer - Additional Information | D36: Validate the mandatory-field messages for the Add Customer Details fields. | E36: Error messages should be displayed for missing mandatory fields in Add Customer Details. | F36: Pending | H36: Pending | I36: 0.25
B37: Cust_028 | C37: Modify Customer | D37: Precondition: The customer should have submitted items. Modify the customer, edit the Group field, review the group list in the dropdown, and select or unselect groups as applicable. | E37: All selected groups should be visible in the Group dropdown. The user should be able to uncheck only groups for which items are not submitted. Groups with submitted items should remain disabled for editing. | F37: Pending | G37: Newly Added | H37: Pending | I37: 1 | J37: 44922
B38: Cust_029 | C38: Update Comments | D38: Add comments for a customer, then edit the comments multiple times and update each time. | E38: The user should be able to edit and update comments each time without issues. | F38: Pending | G38: Newly Added | H38: Pending | I38: 1 | J38: 44922
B39: Cust_030 | C39: Group | D39: Precondition: A group containing "&" should exist in the system, for example Cash & Taxes. Create a customer with the specified group, then modify the customer and select multiple such groups. Review the Customer Listing screen. | E39: The group should be selected correctly and should be reflected consistently across all screens. | F39: Pending | G39: Newly Added | H39: Pending | I39: 1 | J39: 44922
B40: Cust_031 | C40: Create/Modify Customer | D40: Validate the QC and Date Range functionality during customer creation or modification. | E40: After selecting the QC checkbox, the user should be able to add the date range for QC. | F40: Pending | H40: Pending | I40: 1

Sheet Item Creation
B2: Test Case Summary
B3: Total Test Cases | D3: =SUM(D4:D8) | E3: Executed Tests | F3: Total Tests | G3: Automation Scripts
B4: Passed | D4: =COUNTIF(F9:F42,"Passed") | E4: =IF(D4=0,,(D4/(D4+D5))) | F4: =IF(D3=0,,(D4/D3)) | G4: =COUNTIF(H10:H493,"Done")
B5: Failed | D5: =COUNTIF(F9:F110,"Failed") | E5: =IF(D5=0,,(D5/(D5+D6))) | F5: =IF(D3=0,,(D5/D3)) | G5: =COUNTIF(H10:H493,"Failed")
B6: Blocked | D6: =COUNTIF(F9:F110,"Blocked") | E6: =IF(D6=0,,(D6/(D6+D7))) | F6: =IF(D3=0,,(D6/D3)) | G6: =COUNTIF(H10:H493,"Blocked")
B7: Pending | D7: =COUNTIF(F9:F500,"Pending") | E7: =IF(D7=0,,(D7/(D7+D8))) | F7: =IF(D3=0,,(D7/D3)) | G7: =COUNTIF(H10:H493,"Pending")
B8: Not Applicable | D8: =COUNTIF(F9:F110,"Not Applicable") | E8: =IF(D8=0,,(D8/(D8+#REF!))) | F8: =IF(D3=0,,(D8/D3)) | G8: =COUNTIF(H10:H493,"Out of Scope")
B9: S.No. | C9: Module/Sub-Module | D9: Test Steps | E9: Expected Results | F9: Result | G9: Bug ID | H9: Automation Status | I9: Mapped Scripts | J9: Comments
B10: Item_001 | C10: Add Item | D10: Navigate to Spreading > Existing Customer > Action > Add Item. | E10: The Add Item option should be available. | F10: Pending | H10: Done
B11: Item_002 | C11: Add Item - Upload File from System | D11: 1. Open the Add New Item page. 2. Choose the option to browse and add an additional file. | E11: A "Choose File Type To Upload" pop-up with the File Upload field should be displayed. | F11: Pending | H11: Done
B12: Item_003 | C12: Add Item - Upload File from System | D12: 1. Select the file type as PDF, Word, JPEG, or PNG. 2. Click Choose in the File Upload section. 3. Select the file. 4. Click Open. Note: Word files are converted to PDF automatically for spreading. | E12: 1. The selected file category should be applied. 2. Only supported files for the selected category should be shown. 3. The user should be able to change the drive. 4. The file should be uploaded, and a "Successfully uploaded" pop-up should be displayed. | F12: Pending | H12: Done
B13: Item_004 | C13: Add 100 MB File | D13: Select a 100 MB file from the system, upload it, and save the item. | E13: The user should be able to upload the file and save the item. | F13: Pending | H13: Blocked | I13: https://github.com/abramenal/cypress-file-upload/issues/273 | J13: Issue with uploading large size file
B14: Item_005 | C14: Add Different File Formats | D14: Upload the following file formats: Doc, DOCX, RTF Excel (XLSX, XLSM, XLTX) Image (PNG, JPEG) | E14: The system should support all the listed formats. | F14: Pending | H14: Done
B15: Item_006 | C15: Split File - PDF | D15: Add an item and select a PDF file. After upload, review the Split Yes/No option in the ribbon, save the item, and observe the Spread button. | E15: The file should be processed and saved. The Spread button should remain disabled until processing is complete. | F15: Pending | H15: Done
B16: Item_007 | C16: Split File - Excel | D16: Add an item and select an Excel file. Verify that Split is set to No by default for Excel, save the item, and click Spread. | E16: Split should be disabled for Excel, and the Spreading screen should open. | F16: Pending | H16: Done
B17: Item_008 | C17: Split File - PDF | D17: Upload a file, choose Split = No, and add the item. Then modify the item, change Split to Yes, update it, and observe the Spread button. | E17: The user should be able to change Split between Yes and No, and the Spread button should be enabled. | F17: Pending | H17: Done
B18: Item_009 | C18: Document Classification | D18: Upload a file and wait until processing starts. Verify that Document Classification begins and shows percentage progress until completion. | E18: Document Classification should start and display progress. | F18: Pending | H18: Done
B19: Item_010 | C19: Document Classification | D19: Verify that metadata is auto-populated after Document Classification is completed. | E19: Metadata should be auto-populated. | F19: Pending | H19: Done
B20: Item_011 | C20: Document Classification | D20: Verify that the auto-populated metadata matches the uploaded file. Also verify that manually entered values are not overwritten by predictions. | E20: The auto-populated metadata should be correct, and existing manually entered values should not be overwritten. | F20: Pending | H20: Done
B21: Item_012 | C21: Document Classification | D21: Upload an Excel file and observe the Document Classification process. | E21: Document Classification should be disabled for Excel files. | F21: Pending | H21: Done
B22: Item_013 | C22: Notes Processing | D22: Verify that Notes Processing starts and shows percentage progress once the file is processed. | E22: Notes Processing should start. | F22: Pending | H22: Done
B23: Item_014 | C23: Notes Processing | D23: Verify that Notes Processing starts even when AI/ML is set to No. | E23: Notes Processing should start. | F23: Pending | H23: Done
B24: Item_015 | C24: Notes Processing | D24: Verify that Notes Processing is disabled when an Excel file is uploaded. | E24: Notes Processing should be disabled for Excel files. | F24: Pending | H24: Done
B25: Item_016 | C25: Add Item - Upload File from System | D25: After uploading a file, select the language. Then review the prompt for Automatic Table Identification and choose Yes or No. | E25: After the option is selected, a status bar showing Upload, Processed, and Extracted should be displayed. | F25: Pending | H25: Done
... B42: Item_033 | C42: Action Button - Spread | D42: Verify that the user can open the Spreading screen using the Spread option under the Action button. | E42: The Spreading screen should be displayed. | F42: Pending | H42: Done
B43: Item_034 | C43: Action Button - Hold/Unhold | D43: Verify that the user can place an item on hold and remove the hold when an update is required. | E43: The item should move correctly between Hold and Unhold status, and the Hold icon should be displayed when applicable. | F43: Pending | H43: Pending | I43: 0.5
B44: Item_035 | C44: Action Button - Comments | D44: Verify that the Comments icon is enabled when comments are entered for an item. | E44: The added comments and related details should be displayed under the Comments icon. | F44: Pending | H44: Pending | I44: 0.25
B45: Item_036 | C45: Upload Large Files | D45: Upload files of 150 MB, 200 MB, 700 MB, and 1 GB while adding an item. | E45: The user should be allowed to upload files up to 1 GB. | F45: Pending | H45: Blocked | I45: https://github.com/abramenal/cypress-file-upload/issues/273 | J45: Issue with uploading large size file
B46: Item_037 | C46: Item Metadata | D46: Precondition: Group 1 should have multiple mapped models. Group 2 should have one mapped model that is also mapped to Group 1. Add an item from File Store, select Group 2 and review the model and Taxonomy Group. Then select Group 1, choose the same model, and review the Taxonomy Group again. | E46: The Taxonomy Group should always be auto-populated. | F46: Pending | H46: Done
B47: Item_038 | C47: Item Modify | D47: Add an item by uploading a file from the system, save it, then open Actions > Modify, add a new file, and save again. | E47: The item should be modified successfully, and the new file should be added. | F47: Pending | G47: Newly Added | H47: Done
B48: Item_039 | C48: Accountant Name | D48: Add or modify an item and review the Accountant Name field in the metadata section. | E48: The Accountant Name should be displayed in uppercase. | F48: Pending | G48: Newly Added | H48: Pending | I48: 0.25
B49: Item_040 | C49: YTD - Period | D49: On the Add Item screen, select the frequency and then check YTD. | E49: YTD should not change the Period value until a Statement Date is selected. | F49: Pending | G49: Newly Added | H49: Pending | I49: 1
B50: Item_041 | C50: YTD - Period | D50: On the Add Item screen, select the frequency and Statement Date. Then verify YTD behavior for different date ranges: 1. 1 Jan to 14 Jan 2. 15 Jan to 13 Feb 3. 14 Feb to 15 Mar 4. 16 Mar to 14 Apr 5. 15 Apr to 14 May etc. | E50: 1. For dates before 15 Jan, Period should be 0. 2. For 15 Jan to 13 Feb, YTD should be 1. 3. For 14 Feb to 15 Mar, YTD should be 2. 4. For 16 Mar to 14 Apr, YTD should be 3. 5. For 15 Apr to 14 May, YTD should be 4. 6. Subsequent date ranges should continue updating the Period accordingly. | F50: Pending | G50: Newly Added | H50: Pending | I50: 1
B51: Item_042 | C51: YTD Check/Uncheck | D51: On the Add Item screen, select the frequency and Statement Date, check YTD, review the Period, then uncheck YTD and review the Period again. | E51: Checking YTD should set the Period according to the selected Statement Date. Unchecking YTD should revert the change. | F51: Pending | G51: Newly Added | H51: Pending | I51: 1
B52: Item_043 | C52: Split All | D52: Open the Add Item screen, upload a file from the system, select Split = Yes or No, and click the preview after splitting. | E52: The file should not start processing until a Split selection is made. After Split = Yes is selected, processing should begin and the split file should be visible in the preview. | F52: Pending | G52: Newly Added | H52: Done
B53: Item_044 | C53: Split All | D53: On the Add Item screen, upload a file, select Split = No so that processing starts, then change the selection to Yes and review the behavior. | E53: When Split = No is selected, processing should start. If the selection is changed to Yes afterward, a pop-up should indicate that the file will be reprocessed, and processing should restart from 0%. | F53: Pending | G53: Newly Added | H53: Done
B54: Item_045 | C54: Split - Modify Screen | D54: Open any Modify Item screen, upload a file, and review the Split option. | E54: Split should be set to No by default. | F54: Pending | G54: Newly Added | H54: Done
B55: Item_046 | C55: View Item - Filters | D55: Validate the search results using different filters such as Statement Date Range, Status, Frequency, and Audit Method. | E55: Search results should be displayed according to the selected criteria. | F55: Pending | H55: Pending | I55: 0.5
B56: Item_047 | C56: View Item - Reset | D56: Click Reset/Refresh after applying filters. | E56: All search criteria should be reset to the default values. | F56: Pending | H56: Pending | I56: 0.5
B57: Item_048 | C57: View Item - Sent to QC and Direct QC Submit | D57: Validate the functionality for sending an added item to QC or directly submitting it to QC. | E57: The item should be available on the QC screen according to the Reporting Manager access configured for the user. | F57: Pending | H57: Pending | I57: 1
B58: Item_049 | C58: Validate Formula/Validation Stability After Split Change | D58: 1. On the Existing Item screen, click Add Item. 2. Upload a file on the Add Item screen, select No for Split, and click Add Item. 3. Open the Existing Item list and click Spread. 4. On the Spreading screen, map values from the document to the model, click Save as Draft, and go back. 5. Open Modify for the same item, change Split to Yes, click Update Item, and return to the item list. 6. Open Spread again for the same item. | E58: The formula and validation behavior on the model side should remain intact after the Split option is changed. | F58: Pending | H58: Pending | I58: 1

Sheet Spreading Screen_Pdf File
A2: Test Case Summary
A3: Total Test Cases | C3: =SUM(C4:C8) | D3: Executed Tests | E3: Total Tests | F3: Automation Scripts
A4: Passed | C4: =COUNTIF(E9:E249,"Passed") | D4: =IF(C4=0,,(C4/(C4+C5))) | E4: =IF(C3=0,,(C4/C3)) | F4: =COUNTIF(G10:G487,"Done")
A5: Failed | C5: =COUNTIF(E9:E249,"Failed") | D5: =IF(C5=0,,(C5/(C5+C6))) | E5: =IF(C3=0,,(C5/C3)) | F5: =COUNTIF(G10:G487,"Failed")
A6: Blocked | C6: =COUNTIF(E9:E249,"Blocked") | D6: =IF(C6=0,,(C6/(C6+C7))) | E6: =IF(C3=0,,(C6/C3)) | F6: =COUNTIF(G10:G487,"Blocked")
A7: Pending | C7: =COUNTIF(E9:E500,"Pending") | D7: =IF(C7=0,,(C7/(C7+C8))) | E7: =IF(C3=0,,(C7/C3)) | F7: =COUNTIF(G10:G487,"Pending")
A8: Not Applicable | C8: =COUNTIF(E9:E249,"Not Applicable") | D8: =IF(C8=0,,(C8/(C8+#REF!))) | E8: =IF(C3=0,,(C8/C3)) | F8: =COUNTIF(G10:G487,"Out of Scope")
A9: S.No. | B9: Module/Sub-Module | C9: Test Steps | D9: Expected Results | E9: Result | F9: Bug ID | G9: Automation Status | H9: Mapped Scripts | I9: Comments
A10: PDF_001 | B10: Spreading Screen - Landing Page | C10: Click Spread for a customer item on the Existing Items page. Verify that the screen opens on the page where the first zone is detected. If no table is detected, verify that the first page of the PDF opens. | D10: The user should be navigated to the page where the detected zone is tagged automatically. If no table is detected, the first page of the PDF should open. | E10: Pending | F10: Bug 78022 | G10: Done
A11: PDF_002 | B11: Spreading Screen - Zone Option Under Primary Category | C11: Open the Spreading screen and review the default primary category in the document pane. | D11: The Zone option should be displayed under the default primary category. | E11: Pending | G11: Pending | H11: 0.25
A12: PDF_003 | B12: Spreading Screen - Auto-detected Zones | C12: Open the Spreading screen, click Zone under the default primary category, and review the zones detected automatically by the system. | D12: All zones detected automatically by the system should be visible. | E12: Pending | G12: Done
A13: PDF_004 | B13: Spreading Screen - Zone Navigation | C13: Open the Spreading screen and select a zone from the default primary category. | D13: The user should be navigated to the page where the selected zone is tagged automatically. | E13: Pending | G13: Done
A14: PDF_005 | B14: Spreading Screen - Detect Table Option Under Primary Category | C14: Open the Spreading screen and review the default primary category in the document pane. | D14: The Detect Table option should be displayed under the default primary category. | E14: Pending | G14: Pending | H14: 0.25
A15: PDF_006 | B15: Spreading Screen - Detect Table Functionality | C15: 1. Open the Spreading screen. 2. Go to the page where a zone needs to be created in the financial document. 3. Click Detect Table under the primary category. | D15: A table should be created automatically with the detected columns, and Map Mode should be highlighted. | E15: Pending | G15: Done
A16: PDF_007 | B16: Spreading Screen - Tag Table | C16: Tag a detected table by selecting a zone name from the zone-tag dropdown. | D16: The table should be tagged with the selected zone name. | E16: Pending | G16: Done
A17: PDF_008 | B17: Spreading Screen - Line Item Column | C17: 1. Open the Spreading screen. 2. Detect a table on the required page. 3. Verify that the system identifies the line item column automatically. | D17: The selected line item column should be highlighted with a blue marker at the top. | E17: Pending | G17: Done
A18: PDF_009 | B18: Spreading Screen - Draw Table Option Under Primary Category | C18: Open the Spreading screen and review the default primary category in the document pane. | D18: The Draw Table option should be displayed under the default primary category. | E18: Pending | G18: Pending | H18: 0.25
A19: PDF_010 | B19: Spreading Screen - Draw Table Functionality | C19: 1. Go to the page where a zone needs to be created in the financial document. 2. Click Draw Table under the primary category. 3. Drag the cursor over the table area to create the table. | D19: The user should be able to create the table by dragging the cursor. | E19: Pending | G19: Out of Scope
A20: PDF_011 | B20: Spreading Screen - Line Item Column | C20: Verify that the system detects the line item column automatically. | D20: The selected line item column should be highlighted with a blue marker at the top. | E20: Pending | G20: Done
A21: PDF_012 | B21: Spreading Screen - Set Value Column | C21: Right-click the required column in a detected table and select Set Value Column. | D21: The selected column should be marked as the value column and highlighted with a green marker at the top. | E21: Pending | G21: Done
A22: PDF_013 | B22: Spreading Screen - Remove Value Column | C22: 1. Remove the value column when no values are mapped. 2. Remove the value column when values are already mapped. | D22: 1. The value column should be removed. 2. If mapped values exist, they should be converted to free text when the value column is removed. | E22: Pending | G22: Done
A23: PDF_014 | B23: Spreading Screen - Switch Value Column | C23: Switch the value column and verify the autofill behavior. | D23: The value column should be changed, and autofill should use the newly selected value column. | E23: Pending | G23: Done
A24: PDF_015 | B24: Spreading Screen - Visual Cue | C24: Select a value from the value column of a table and review the visual cue. | D24: The selected value should be displayed in the visual cue. | E24: Pending | G24: Done
A25: PDF_016 | B25: Spreading Screen - Optical Mapping | C25: Map a value from the financial statement to a model cell by single-clicking or double-clicking a value in the detected or drawn table and then mapping it to the model. | D25: The selected value should be mapped to the model. | E25: Pending | G25: Done
A26: PDF_017 | B26: Spreading Screen - Map Mode Toggle Visibility | C26: Open the Spreading screen and review the default primary category in the document pane. | D26: The Map Mode toggle should be displayed under the default primary category. | E26: Pending | G26: Pending | H26: 0.25
A27: PDF_018 | B27: Spreading Screen - Map/Edit Mode Toggle Action | C27: Open the Spreading screen and click the Map Mode toggle. | D27: After the toggle is clicked, the label should switch from Map Mode to Edit Mode. | E27: Pending | G27: Done
A28: PDF_019 | B28: Spreading Screen - Map Mode Functionality | C28: Open the Spreading screen, keep Map Mode active, map a few values from the current page to the model, and then click Mapped Values in the ribbon. | D28: All values mapped from the current page should be displayed in the Mapped Values pop-up. | E28: Pending | G28: Done
A29: PDF_020 | B29: Spreading Screen - Edit Mode Toggle Visibility | C29: Open the Spreading screen and click the Map Mode toggle. | D29: After the toggle is clicked, the button should switch to Edit Mode. | E29: Pending | G29: Done
A30: PDF_021 | B30: Spreading Screen - Edit Mode Functionality | C30: Open the Spreading screen, switch from Map Mode to Edit Mode, and review the table-editing behavior. | D30: The user should be able to edit table values in Edit Mode and continue mapping as supported. | E30: Pending | G30: Done
A31: PDF_022 | B31: Spreading Screen - Disable Single Click Toggle Visibility | C31: Open the Utilities dropdown on the Spreading screen. | D31: The Disable Single Click mapping option should be available and should be disabled by default. | E31: Pending | G31: Done
A32: PDF_023 | B32: Spreading Screen - Enable Single Click Toggle Visibility | C32: Open the Utilities dropdown, review the Disable Single Click option, and toggle it. | D32: The toggle should be enabled, and the label should switch to Enable Single Click. | E32: Pending | G32: Done
A33: PDF_024 | B33: Spreading Screen - Disable Single Click Mapping Functionality | C33: Open the Utilities dropdown, keep Disable Single Click active, and then map a value from the document to the model. | D33: The user should be able to map the value only by double-clicking. | E33: Pending | G33: Done
A34: PDF_025 | B34: Spreading Screen - Enable Single Click Mapping Functionality | C34: Open the Utilities dropdown, switch the toggle to Enable Single Click, and then map a value from the document to the model. | D34: The user should be able to map the value by single-clicking. | E34: Pending | G34: Done
A35: PDF_026 | B35: Spreading Screen - Merge Mode | C35: In Merge Mode, select two consecutive rows in a table where a line item is split across rows, then right-click and choose Merge Row(s). | D35: The selected rows should be merged. | E35: Pending | G35: Done
A36: PDF_027 | B36: Spreading Screen - Split Rows | C36: After merging rows, select the merged row and choose Split Row(s) from the right-click menu. | D36: The merged row should be split back into separate rows. | E36: Pending | G36: Done
A37: PDF_028 | B37: Spreading Screen - Clear Zone Icon | C37: Clear a zone from the current page by clicking the clear icon next to the zone name under the relevant category. | D37: The selected zone should be removed from the document pane, and any mapping from that zone to the model should also be removed. | E37: Pending | G37: Done
A38: PDF_029 | B38: Spreading Screen - Doc to Model Option Visibility | C38: Open the Navigation category in the document pane. | D38: The Doc to Model option should be displayed under the Navigation category. | E38: Pending | G38: Done
... A46: PDF_037 | B46: Spreading Screen - Split Window Functionality | C46: Use the Split Window option on the Spreading screen to split the financial document into two panes. | D46: The document should be displayed in two panes. | E46: Pending | G46: Done
A47: PDF_038 | B47: Spreading Screen - Split Window Mapping Functionality | C47: Enable Split Window and map values using either pane. | D47: The user should be able to map values from both panes. | E47: Pending | F47: 70985 | G47: Done
A48: PDF_039 | B48: Spreading Screen - Close Split Window Pane | C48: Close the split window pane after opening Split Window. | D48: The extra pane should be closed, and the document should return to a single-pane view. | E48: Pending | G48: Done
A49: PDF_040 | B49: Spreading Screen - Customer Zone | C49: Create a Customer Zone from the Spreading screen and review the new zone entry. | D49: The Customer Zone should be created successfully and should be available for use. | E49: Pending | G49: Done
A50: PDF_041 | B50: Customer Zone - Duplicate | C50: Create a Customer Zone that already exists in the list. Then try to create a Customer Zone with the same name as an existing Global Zone. | D50: A duplicate zone should not be created in either case. | E50: Pending | G50: Done
A51: PDF_042 | B51: Spreading Screen - Mapping from Customer Zone | C51: Create or detect a table, tag it with a Customer Zone, set the value column, pick a value from the value column, and map it to a model cell. | D51: The value from the Customer Zone should be mapped to the selected model cell. | E51: Pending | G51: Done
A52: PDF_043 | B52: Spreading Screen - Rotate Option Visibility | C52: Open the Secondary category in the document pane and review the available options. | D52: The Rotate option should be displayed under the Secondary category. | E52: Pending | G52: Done
A53: PDF_044 | B53: Spreading Screen - Rotate Functionality | C53: Click the Rotate option under the Secondary category. | D53: The current page of the document should rotate clockwise. | E53: Pending | G53: Done
A54: PDF_045 | B54: Spreading Screen - Clean File Option Visibility | C54: Open the Secondary category in the document pane and review the available options. | D54: The Clean File dropdown should be displayed under the Secondary category. | E54: Pending | G54: Done
A55: PDF_046 | B55: Spreading Screen - Clean File Dropdown Options | C55: Open the Secondary category, click Clean File, and review the dropdown options. | D55: The Clean File dropdown should display Enable and Reset options for Single Page and All Pages. | E55: Pending | G55: Done
A56: PDF_047 | B56: Spreading Screen - Clean File Enable Functionality | C56: Open Clean File from the Secondary category, click Enable, and verify Clean PDF behavior for No Despeckle, Low Despeckle, and High Despeckle. | D56: The Clean File pop-up should open, and cleaning should work for all supported options. | E56: Pending | G56: Done
A57: PDF_048 | B57: Spreading Screen - Clean File Reset (Single Page) | C57: Open Clean File, click Enable, select Single Page in the pop-up, apply cleaning using the available despeckle options, click Accept, and then use Reset for Single Page. | D57: The selected page should be restored to the original page. | E57: Pending | G57: Done
A58: PDF_049 | B58: Spreading Screen - Clean File Reset (All Pages) | C58: Open Clean File, click Enable, select All Pages in the pop-up, apply cleaning using the available despeckle options, click Accept, and then use Reset for All Pages. | D58: All selected pages should be restored to the original file. | E58: Pending | G58: Done
A59: PDF_050 | B59: Spreading Screen - Clean File Despeckle Options | C59: Open Clean File, click Enable, and verify the despeckle options in the pop-up for Low, High, and Reset. | D59: The selected despeckle setting should be applied correctly. Reset should restore the original PDF page. | E59: Pending | G59: Done
... A98: PDF_089 | B98: Spreading Screen - Validation | C98: Verify the submit behavior for both validation states: 1. When the validation icon is green. 2. When the validation icon is red. | D98: 1. When the validation icon is green, the spread should be submitted without validation-related errors. 2. When the validation icon is red, the validation issues must be cleared before the spread can be submitted. | E98: Pending | G98: Out of Scope
A99: PDF_090 | B99: Spreading Screen - Validation | C99: Verify validation behavior based on the configured validation switch settings. | D99: If the validation status is green, no configuration change should be required. If the validation status is red, the configuration should be updated as applicable. | E99: Pending | G99: Out of Scope | I99: [Needs QA Review: original wording ambiguous]
A100: PDF_091 | B100: Spreading Screen - Autofill | C100: Verify that Autofill works only for zones tagged in the document. Clear a zone and tag it again so that the zone is treated as new, then run Autofill and review the expression update. | D100: Autofill should work for zones that are cleared and tagged again, and NA values in the base expression should be replaced with values mapped from the new zone where applicable. | E100: Pending | G100: Done
A101: PDF_092 | B101: Spreading Screen - Autofill | C101: 1. Set a value column in the tagged zone. 2. Click Autofill. 3. Review the model cells autofilled from the tagged zone. | D101: Expressions should be loaded only for cells that are autofilled after the Autofill action is triggered. | E101: Pending | G101: Done
A102: PDF_093 | B102: Spreading Screen - Autofill | C102: Verify Autofill when an expression contains multiply or divide operators and one mapped value is missing. | D102: The missing value in the expression should be replaced with NA. The expression should not be computed with NA, so the cell may display #NAME as applicable. | E102: Pending | G102: Done
A103: PDF_094 | B103: Spreading Screen - Autofill | C103: Verify Autofill when an expression contains only plus and minus operators and one mapped value is missing. | D103: The expression should be adjusted automatically when only plus and minus operators are present. | E103: Pending | G103: Done
A104: PDF_095 | B104: Spreading Screen - Autofill | C104: Verify that adding a data column, removing a data column, switching a data column, clearing a zone, or deleting a zone causes the zone to be treated as new. Then run Autofill again. | D104: The zone should be processed again as a new zone, and Autofill should rerun for that zone. | E104: Pending | G104: Done
A105: PDF_096 | B105: Spreading Screen - Autofill | C105: Detect a new zone, add a missing zone, or clear an already tagged zone, and then review the Autofill button state. | D105: The Autofill button in the ribbon should be enabled. | E105: Pending | G105: Done
A106: PDF_097 | B106: Spreading Screen - Autofill | C106: Click Clear Zone and review the affected expression based on the base spread. | D106: NA should replace the mapped value that came from the cleared zone. | E106: Pending | G106: Done
A107: PDF_098 | B107: Spreading Screen - Autofill | C107: Map a new value into a cell that is not part of the base-spread expression, then run Autofill again. | D107: The newly mapped value that is not part of the base expression should be retained after Autofill. | E107: Pending | G107: Done
A108: PDF_099 | B108: Spreading Screen - Edit Spread | C108: Select the Base Spread column and click Edit Spread. | D108: The selected Base Spread should be enabled for editing, and the current spread should be saved. | E108: Pending | G108: Done
A109: PDF_100 | B109: Spreading Screen - Edit Spread | C109: Make manual changes in the Base Spread. | D109: Only manual changes should be allowed in the Base Spread. | E109: Pending | G109: Done
A110: PDF_101 | B110: Spreading Screen - Autofill | C110: Verify that Spreadsmart retains expressions in which ribbon tools were applied. | D110: Cells with ribbon-based functions should be remembered by the system during Autofill. | E110: Pending | G110: Done
A111: PDF_102 | B111: Spreading Screen - Autofill | C111: Verify that Unit Scale operations are not retained during Autofill. | D111: Unit Scale should not be reapplied to cells during Autofill. | E111: Pending | G111: Done
... A133: PDF_124 | B133: String Data Cell | C133: Map values into a String cell, perform Submit and Continue, and run Autofill. Then map free text into the same String cell, change the value column, and review the warning about data loss. | D133: The user should be able to Autofill values into the String cell. Free text should be mapped correctly, and the values should be removed when the value column is removed. | E133: Pending | G133: Done
A134: PDF_125 | B134: DateTime Cell | C134: Insert a new row on the Spreading screen, set the data type to DateTime, map a year to the cell, and review the mapped value from the Mapped Cells ribbon. | D134: A DateTime cell should be added, the year should be entered successfully, and the Mapped Cells view should display the correct value. | E134: Pending | G134: Blocked | I134: Issue still exists. Functionality not clear https://dev.azure.com/ITC-ProductPlatforms/Spreadsmart%20V2/_workitems/edit/66452
A135: PDF_126 | B135: Validations Modify | C135: Modify a validation formula on the Spreading screen, add a number using the + operator, remove it, and then submit the spread when the validation becomes TRUE. | D135: The user should be able to modify the validation, add and remove the number, and submit the spread successfully. | E135: Pending | G135: Done
A136: PDF_127 | B136: Expression | C136: Map values to build the expression (A+B+C), then replace the + operator with a conversion of Divide by 100 and review the expression. | D136: The expression should be updated to A/100+B+C. | E136: Pending | F136: Existing bug. | G136: Done
A137: PDF_128 | B137: Expression | C137: Map values using Negative, Contra, and Absolute operations to form NEG(A+B+C). Then click Clear Zone and review the expression cell. | D137: The expression should become blank after the zone is cleared. The expression cell may display junk data or #NAME, as observed in the original scenario. | E137: Pending | G137: Done | I137: [Needs QA Review: original scenario documents intermittent behavior]
A138: PDF_129 | B138: Expression | C138: Map values using Unit Scale and Conversion to form ((A+B+C)/10)*100. Select the full expression in the formula bar, map another value from the file, and review the expression cell. | D138: The expression should either update correctly or remain unchanged. The expression cell may display junk data or #NAME, as observed in the original scenario. | E138: Pending | G138: Done | I138: [Needs QA Review: original scenario documents intermittent behavior]
A139: PDF_130 | B139: Expression | C139: Map values using operators from the menu bar to build an expression such as (A+B-C*D+E/F). Then validate Clear Zone and Autofill behavior and review the expression cell. | D139: The expression should behave according to the defined operations. The cell may display junk values in the expression, as noted in the original scenario. | E139: Pending | G139: Done | I139: [Needs QA Review: original scenario references console-log validation and intermittent behavior]
A140: PDF_131 | B140: Exclusion - Brackets | C140: Precondition: Template line item = Cash and revenue; spreading line item = a) Cash and revenue. Set a zone, select a value column, and run Autofill from the template. Then add prefixes such as a), b), and c) in Exclusion Management and run Autofill again. | D140: Case 1: Autofill should not occur when there is no applicable opening bracket scenario for excluding inner text. Case 2: Autofill should occur after the prefix is added in Exclusion Management. | E140: Pending | G140: Done
A141: PDF_132 | B141: Customer Taxonomy | C141: Use Global Taxonomy in a spread, perform Submit and Continue, switch data columns, run Autofill, and then submit the spread. When the Undo Customer Taxonomy pop-up appears, check and uncheck keywords and submit again. | D141: The user should be able to submit and autofill the spread. The Undo Customer Taxonomy pop-up should display related keywords, and the check/uncheck behavior should work correctly. | E141: Pending | F141: 71133 | G141: Done
A142: PDF_133 | B142: Edit Table | C142: 1. Open the Spreading screen and click Detect Table under the default primary category. 2. Merge the first and second columns and set the third column as the value column. 3. Switch to Edit Mode and draw a column between the first and second columns. 4. Review whether the value column shifts to the left, then remove the shifted value column. | D142: The user should be able to edit the columns, and the value column should be removable. | E142: Pending | F142: 71074 | G142: Out of Scope
A143: PDF_134 | B143: Exclusion - Free Text | C143: Select free text from a paragraph, map values that include currency and units, and verify that exclusion rules are applied correctly during mapping. | D143: The values should be mapped without errors or incorrect exclusion behavior. | E143: Pending | G143: Done
A144: PDF_135 | B144: Exclusion - Free Text | C144: Verify exclusion handling for values with: 1. a closing bracket and dot `)` 2. only an opening bracket `(` 3. `/-` | D144: Exclusion should be applied correctly, and the value should be mapped. | E144: Pending | G144: Done
A145: PDF_136 | B145: Exclusion - Free Text | C145: Run Autofill for values with a closing bracket and dot, only an opening bracket, and `/-`. | D145: Autofill should work for all listed cases, and exclusion should be applied correctly. | E145: Pending | G145: Done
A146: PDF_137 | B146: Exclusion - Free Text | C146: Map a value in the format `(value)` to the model and then verify Autofill for the same case. | D146: The value should remain unchanged, exclusion should not be applied in this case, and Autofill should work correctly. | E146: Pending | G146: Done
A147: PDF_138 | B147: Spreading Adjustments | C147: Adjust the screen using zoom in and zoom out from the model side, exit full-screen mode, and verify the saved adjustments in Template Configuration, Spreading, and Quality Check screens. | D147: The adjustments should be retained in both full-screen and normal-screen views across all listed screens. | E147: Pending | G147: Done
A148: PDF_139 | B148: Exclusion on Header Row | C148: Detect a table, set a Header Row, map values from a matrix table, and verify a header row containing prefix or suffix text and values. Perform Submit and Continue, run Autofill, then delete or modify the header-row prefix/suffix and run Autofill again. | D148: The user should be able to detect the table and set the Header Row. During Autofill, prefix and suffix currency text should be excluded. | E148: Pending | G148: Done
A149: PDF_140 | B149: Exclusion on Header Row | C149: Detect a table, set a Header Row, map values from a matrix table, and verify a header row containing currencies. Perform Submit and Continue, run Autofill, then replace or delete the currency in the header row and run Autofill again. | D149: The user should be able to detect the table and set the Header Row. During Autofill, prefix and suffix currency text should be excluded. | E149: Pending | G149: Done | I149: ..\Downloads\Currency List (2).xlsx
A150: PDF_141 | B150: Disabled Ribbon Button | C150: Open the Autofill dropdown and review options such as Current Page, All Pages, and All Keywords. Verify disabled-button behavior in different conditions, including Error Logs, and try clicking disabled buttons. | D150: Disabled buttons should not be clickable. The disabled icon should be shown, and no action should occur. | E150: Pending | G150: Done
A151: PDF_142 | B151: Duplicate Model Account | C151: Insert a new row, enter a duplicate model account, review the warning message, and click OK. | D151: The Insert Row pop-up should warn that a similar account already exists and that clicking OK will create a duplicate account. After clicking OK, the duplicate model account should be added. | E151: Pending | G151: Done
A152: PDF_143 | B152: Submit Spread - Manual Values | C152: Map a few values, enter a manual value in any cell, and submit the spread. | D152: The spread should be submitted successfully with a manual value present. | E152: Pending | G152: Done
A153: PDF_144 | B153: Submit Spread - Manual String Value | C153: Map a few values, insert a String-type row, enter a manual value, and submit the spread. | D153: The spread should be submitted successfully with manual String data. | E153: Pending | G153: Done
A154: PDF_145 | B154: Matrix Zone | C154: Detect or draw a table, set the zone, select a row, and right-click it. | D154: The table should be created, zone tagging should be available, the selected zone should be applied to the table, and the relevant context-menu options should be displayed. | E154: Pending | G154: Done
A155: PDF_146 | B155: Matrix Zone | C155: Select Set Header Row from the available options. | D155: The selected row should be set as the Header Row. | E155: Pending | G155: Done
A156: PDF_147 | B156: Matrix Zone | C156: Click a value cell in the matrix zone. | D156: Two visual cues should be displayed: one for the line item and one for the Header Row. | E156: Pending | G156: Done
A157: PDF_148 | B157: Matrix Zone | C157: Verify that all columns except the line item column are marked with a green underline. | D157: All columns except the line item column should have a green underline. | E157: Pending | G157: Done
A158: PDF_149 | B158: Matrix Zone | C158: Verify that all line-item rows below the Header Row are marked in green. | D158: All applicable line-item rows below the Header Row should be marked in green. | E158: Pending | G158: Done
A159: PDF_150 | B159: Matrix Zone | C159: Map a value from below the Header Row to the model. | D159: The value should be mapped successfully. | E159: Pending | G159: Done
A160: PDF_151 | B160: Matrix Zone | C160: Select a value below the Header Row and modify the Header Row text through the visual cue. | D160: The Header Row value should be updated, and a manual-entry icon should be displayed. | E160: Pending | G160: Done
A161: PDF_152 | B161: Matrix Zone | C161: Select a value above the Header Row and map it to the model. | D161: The value should be mapped as free text. | E161: Pending | G161: Done
... A181: PDF_172 | B181: Spreading Screen - Visual Cue | C181: Hover over the same mapped cell after the visual-cue update. | D181: The updated value should be displayed along with the manual-entry indication. | E181: Pending | G181: Done
A182: PDF_173 | B182: Validations Popup | C182: Add a validation in the model in a format such as sum(A+B)>=0, map values on the Spreading screen, open the Validation pop-up, and review the calculated value in both Pass and Fail tabs. | D182: The Validation pop-up should display the correct calculated value. | E182: Pending | F182: 79846 | G182: Done
A183: PDF_174 | B183: Base Ribbon Buttons | C183: Open the Base Spread by double-clicking it on the Spreading screen. | D183: The following buttons should be disabled: | E183: Pending | G183: Done
C184: Review the ribbon buttons. | D184: Detect Table / Draw Table | E184: Pending
C185: Verify which ribbon buttons are disabled and which remain enabled. | D185: Edit Mode, Map Mode, Merge Mode | E185: Pending
D186: Clear Zone, Show/Hide Smart Fill | E186: Pending
...

Sheet Spreading Screen_Excel File
B2: Test Case Summary
B3: Total Test Cases | D3: =SUM(D4:D8) | E3: Executed Tests | F3: Total Tests
B4: Passed | D4: =COUNTIF(F9:F1500,"Passed") | E4: =IF(D4=0,,(D4/(D4+D5))) | F4: =IF(D3=0,,(D4/D3))
B5: Failed | D5: =COUNTIF(F9:F1500,"Failed") | E5: =IF(D5=0,,(D5/(D5+D6))) | F5: =IF(D3=0,,(D5/D3))
B6: Blocked | D6: =COUNTIF(F9:F1500,"Blocked") | E6: =IF(D6=0,,(D6/(D6+D7))) | F6: =IF(D3=0,,(D6/D3))
B7: Pending | D7: =COUNTIF(F9:F1500,"Pending") | E7: =IF(D7=0,,(D7/(D7+D8))) | F7: =IF(D3=0,,(D7/D3))
B8: Not Applicable | D8: =COUNTIF(F9:F150,"Not Applicable") | E8: =IF(D8=0,,(D8/(D8+#REF!))) | F8: =IF(D3=0,,(D8/D3))
B9: S.No. | C9: Module/Sub-Module | D9: Test Steps | E9: Expected Results | F9: Result | G9: Bug ID | H9: Comments
B10: Excl_001 | C10: Spreading screen - Landing Page | D10: 1. Log in and navigate to the Dashboard page. 2. On the Dashboard page, click the Spreading tab and verify that the "Create Customer" text link is visible. 3. Click "Create Customer", enter the required details, and click Create. 4. On the Customer screen, verify that the "Add Item" button is visible and click it. 5. On the Add Item screen, upload the Excel file and enter values in all mandatory fields. 6. Click "Add Item" and proceed to the item details screen. 7. Add the remaining item details and save the item. | E10: The user should be able to create an item for an Excel file. | F10: Pending
B11: Excl_002 | C11: Spreading screen | D11: 1. Log in and navigate to the Dashboard page. 2. On the Dashboard page, click the Spreading tab and verify that the "Create Customer" text link is visible. 3. Click "Create Customer", enter the required details, and click Create. 4. On the Customer screen, verify that the "Add Item" button is visible and click it. 5. On the Add Item screen, upload the Excel file and enter values in all mandatory fields. 6. Click "Add Item" and proceed to the item details screen. 7. Review the "Spread" action for created item and click it and it should navigate to Spreading screen. | E11: The Spreading screen should open. | F11: Pending
B12: Excl_003 | C12: Spreading screen - Drawtable | D12: Verify the Draw Table functionality under the primary category by performing the steps below: 1. Go to a tab where zone needs to be dropped in the left pane of the financial document on the Spreading screen. 2. Click Draw Table option under Primary Category. 3. Drag the cursor over the table for table creation. | E12: The user should be able to create a table by dragging the cursor. | F12: Pending
B13: Excl_004 | C13: Spreading screen - Tag Table | D13: Verify that the user can tag a table by opening the "Select Zone" dropdown in the toolbar and selecting the required tag or zone name. Click the tick mark next to the zone dropdown to confirm the zone selection. | E13: The selected tag/zone name should be applied to the zone. | F13: Pending
B14: Excl_005 | C14: Spreading screen- Show/Hide Zone Name | D14: Open the Spreading screen and click Secondary Category. Review the "Show/Hide Zone Name" option. Verify that the user can show or hide the zone name after selecting the Show/Hide Zone Name option. | E14: The user should be able to show or hide the zone name. | F14: Pending
B15: Excl_006 | C15: Spreading screen - Line Item Column | D15: Verify that the system detects the line item column automatically. | E15: The selected line item column should be highlighted with a blue marker at the top. | F15: Pending
B16: Excl_007 | C16: Spreading screen - Set Value Column | D16: Verify that the user can set a value column by placing the cursor on the required column, right-clicking, and selecting Set Value Column from the context menu. | E16: The selected value column should be highlighted with a green marker at the top. | F16: Pending
B17: Excl_008 | C17: Spreading screen -Remove Value Column | D17: Verify that the value column can be removed when no values are mapped. Verify that the value column can be removed when values are already mapped. | E17: 1. The value column should be removed. 2. The mapped values should be added as free text when the value column is removed. | F17: Pending
B18: Excl_009 | C18: Spreading screen - Switch Value Column | D18: Verify that the value column can be switched and that Autofill uses the updated value column. | E18: The value column should be updated, and Autofill should use the selected value column for data. | F18: Pending
B19: Excl_010 | C19: Spreading screen - Visual Cue | D19: Verify that the user can select a value from the value column and review it in the visual cue. | E19: The selected value should be displayed in the visual cue. | F19: Pending
B20: Excl_011 | C20: Spreading screen - Optical Mapping | D20: Verify that the user can map a value from the financial statement to a model cell by single-clicking or double-clicking the value in the detected or drawn table. | E20: The value should be mapped to the model. | F20: Pending
B21: Excl_012 | C21: Spreading screen - Edit Mode | D21: 1. Log in and navigate to the Dashboard page. 2. On the Dashboard page, click the Spreading tab and verify that the "Create Customer" text link is visible. 3. Click "Create Customer", enter the required details, and click Create. 4. On the Customer screen, verify that the "Add Item" button is visible and click it. 5. On the Add Item screen, upload the Excel file and enter values in all mandatory fields. 6. Click "Add Item" and proceed to the item details screen. 7. Verify the provision to remove columns and add columns in the detected table using Edit Mode by executing below steps: Review the default open Primary Category having radio button with Map Mode enabled state. Click enabled state Map Mode and view the Edit Mode is in enabled state. User is perform action double-click the column which needs to be removed or Double click at position where column needs to be added. | E21: The column should be added or removed successfully. | F21: Pending
... B31: Excl_022 | C31: Spreading screen - Despeckle | D31: 1. Log in and navigate to the Dashboard page. 2. On the Dashboard page, click the Spreading tab and verify that the "Create Customer" text link is visible. 3. Click "Create Customer", enter the required details, and click Create. 4. On the Customer screen, verify that the "Add Item" button is visible and click it. 5. On the Add Item screen, upload the Excel file and enter values in all mandatory fields. 6. On the Spreading screen, open the Secondary Category menu. 7. Review the "Clean Page" ribbon option under Secondary Category. | E31: The "Clean Page" ribbon option should not be displayed for Excel files. | F31: Pending
B32: Excl_023 | C32: Spreading screen - Split Window | D32: 1. Log in and navigate to the Dashboard page. 2. On the Dashboard page, click the Spreading tab and verify that the "Create Customer" text link is visible. 3. Click "Create Customer", enter the required details, and click Create. 4. On the Customer screen, verify that the "Add Item" button is visible and click it. 5. On the Add Item screen, upload the Excel file and enter values in all mandatory fields. 6. On the Spreading screen, open the Secondary Category menu. 7. Review the "Split Window" ribbon option under Secondary Category. | E32: Values that have been picked from two different pages should be mapped to the cell of the model. | F32: Pending | G32: 70919
B33: Excl_024 | C33: Spreading screen - Close Split Pane | D33: 1. Log in and navigate to the Dashboard page. 2. On the Dashboard page, click the Spreading tab and verify that the "Create Customer" text link is visible. 3. Click "Create Customer", enter the required details, and click Create. 4. On the Customer screen, verify that the "Add Item" button is visible and click it. 5. On the Add Item screen, upload the Excel file and enter values in all mandatory fields. 6. On the Spreading screen, open the Secondary Category menu. 7. Review the "Split Window" ribbon option under Secondary Category and excel page will be divided into two panes. 8. Verify Split panes view should get closed by click the Split button again. | E33: The normal document view should be displayed. | F33: Pending
B34: Excl_025 | C34: Spreading screen - Customer Zone | D34: 1. Log in and navigate to the Dashboard page. 2. On the Dashboard page, click the Spreading tab and verify that the "Create Customer" text link is visible. 3. Click "Create Customer", enter the required details, and click Create. 4. On the Customer screen, verify that the "Add Item" button is visible and click it. 5. On the Add Item screen, upload the Excel file and enter values in all mandatory fields. 6. Navigate to Spreading screen and view the "Draw Table" option under default open Primary Category. 7. Click "Draw Table" and then select table and view the 'Select zone" is enabled in state. 8. Click "Select zone" dropdown field and view the "Add Customer Zone" button and click it. 9. Verify that the user can create a Customer Zone by clicking the add Customer Zone button and providing a name to the zone and clicking Add Zone button in the popup. | E34: The Customer Zone should be added to the list of zones. | F34: Pending
B35: Excl_026 | C35: Spreading screen - Mapping from Customer Zone | D35: 1. Log in and navigate to the Dashboard page. 2. On the Dashboard page, click the Spreading tab and verify that the "Create Customer" text link is visible. 3. Click "Create Customer", enter the required details, and click Create. 4. On the Customer screen, verify that the "Add Item" button is visible and click it. 5. On the Add Item screen, upload the Excel file and enter values in all mandatory fields. 6. Navigate to Spreading screen and view the "Draw Table" option under default open Primary Category. 7. Click "Draw Table" and then select table and view the 'Select zone" is enabled in state. 8. Click "Select zone" dropdown field and view the "Add Customer Zone" button and click it and zone should be added. 9. Verify that the user can tag a zone with the Customer Zone and map the value to the model from the Customer Zone. 10. Draw a table. 11. Tag with Customer Zone name. 12. Specify value column and pick a value from the value column. 13. Map it to a cell of the model. | E35: Value from the Customer Zone should be mapped to a cell of the model. | F35: Pending
B36: Excl_027 | C36: Spreading screen - Rotate | D36: 1. Log in and navigate to the Dashboard page. 2. On the Dashboard page, click the Spreading tab and verify that the "Create Customer" text link is visible. 3. Click "Create Customer", enter the required details, and click Create. 4. On the Customer screen, verify that the "Add Item" button is visible and click it. 5. On the Add Item screen, upload the Excel file and enter values in all mandatory fields. 6. On the Spreading screen, open the Secondary Category menu. 7. Review the "Rotate" ribbon option under Secondary Category. | E36: No "Rotate" ribbon option should be displayed and it should be hidden in case of excel files. | F36: Pending
B37: Excl_028 | C37: Spreading screen - Watermark | D37: Verify that Watermark option is disabled for Excel file. | E37: Option should be disabled. | F37: Pending | G37: Verified with Clean pdf.
B38: Excl_029 | C38: Spreading screen - Information Icon (i) | D38: 1. Log in and navigate to the Dashboard page. 2. On the Dashboard page, click the Spreading tab and verify that the "Create Customer" text link is visible. 3. Click "Create Customer", enter the required details, and click Create. 4. On the Customer screen, verify that the "Add Item" button is visible and click it. 5. On the Add Item screen, upload the Excel file and enter values in all mandatory fields. 6. Navigate to Spreading screen and view the "Info" icon in left corner near "Utilities" dropdown option and click it. 7. Base spread popup should get opened with all details. | E38: A popup should be visible with the details. | F38: Pending
B39: Excl_030 | C39: Spreading screen - Base Spread | D39: 1. Log in and navigate to the Dashboard page. 2. On the Dashboard page, click the Spreading tab and verify that the "Create Customer" text link is visible. 3. Click "Create Customer", enter the required details, and click Create. 4. On the Customer screen, verify that the "Add Item" button is visible and click it. 5. On the Add Item screen, upload the Excel file and enter values in all mandatory fields. 6. Navigate to Spreading screen and view the "Utilities" dropdown option in left corner and then click it and user can see the "Base spread" option and click it. 7. Base spread popup should get opened with all details. 8. Verify that the user can change the base period by clicking the Base Spread button in the ribbon and selecting the relevant base in the popup. | E39: Values in the current period column should be removed and base period should get changed. | F39: Pending
B40: Excl_031 | C40: Spreading screen - Base Spread | D40: 1. Log in and navigate to the Dashboard page. 2. On the Dashboard page, click the Spreading tab and verify that the "Create Customer" text link is visible. 3. Click "Create Customer", enter the required details, and click Create. 4. On the Customer screen, verify that the "Add Item" button is visible and click it. 5. On the Add Item screen, upload the Excel file and enter values in all mandatory fields. 6. Navigate to Spreading screen and view the "Utilities" dropdown option in left corner and then click it and user can see the "Base spread" option and click it. 7. Base spread popup should get opened with all details. Precondition: At least 5-6 items should be available in spread state. Launch Spreading screen > click to change the base spread. Select base spread from the list. Then again repeat the steps for all the available base spreads. | E40: The user should be able to change the base spread. When change the base spread, data for current should be reset. The user should be able to set base spread mutiple times when changed. | F40: Pending
B41: Excl_032 | C41: Spreading screen - Base Spread | D41: 1. Log in and navigate to the Dashboard page. 2. On the Dashboard page, click the Spreading tab and verify that the "Create Customer" text link is visible. 3. Click "Create Customer", enter the required details, and click Create. 4. On the Customer screen, verify that the "Add Item" button is visible and click it. 5. On the Add Item screen, upload the Excel file and enter values in all mandatory fields. 6. Navigate to Spreading screen and view the "Utilities" dropdown option in left corner and then click it and user can see the "Base spread" option and click it. 7. Base spread popup should get opened with all details. 8. Verify that once user change the base spread>data should be reset. Set zones again and autofill. | E41: The user should be able to autofill data as per the select base item. | F41: Pending
B42: Excl_033 | C42: Spreading screen - Base Spread | D42: 1. Log in and navigate to the Dashboard page. 2. On the Dashboard page, click the Spreading tab and verify that the "Create Customer" text link is visible. 3. Click "Create Customer", enter the required details, and click Create. 4. On the Customer screen, verify that the "Add Item" button is visible and click it. 5. On the Add Item screen, upload the Excel file and enter values in all mandatory fields. 6. Navigate to Spreading screen and view the "Utilities" dropdown option in left corner and then click it and user can see the "Base spread" option and click it. 7. Base spread popup should get opened with all details. 8. Navigate to base spread > click edit item button. 9. Make manual changes and save. 10. Try to map data from table > observe. | E42: Edit button should show the popup to make changes to base spread. Manual changes should be saved. The user should not be able to map any values from table. | F42: Pending
B43: Excl_034 | C43: Spreading screen - Load Spreads | D43: 1. Log in and navigate to the Dashboard page. 2. On the Dashboard page, click the Spreading tab and verify that the "Create Customer" text link is visible. 3. Click "Create Customer", enter the required details, and click Create. 4. On the Customer screen, verify that the "Add Item" button is visible and click it. 5. On the Add Item screen, upload the Excel file and enter values in all mandatory fields. 6. Navigate to Spreading screen and view the "Utilities" dropdown option in left corner and then click it and user can see the "Load spread" option and click it. 7. Load spread popup should get opened with all details. 8. Verify that the user can load the spreads pertaining to the customers in the model pane on the Spreading screen by clicking the Load Spread button and selecting spreads (maximum 18 spreads can be selected). | E43: All selected spreads should get rendered in the model pane on the Spreading screen. | F43: Pending
B44: Excl_035 | C44: Spreading screen - Load Spreads | D44: 1. Log in and navigate to the Dashboard page. 2. On the Dashboard page, click the Spreading tab and verify that the "Create Customer" text link is visible. 3. Click "Create Customer", enter the required details, and click Create. 4. On the Customer screen, verify that the "Add Item" button is visible and click it. 5. On the Add Item screen, upload the Excel file and enter values in all mandatory fields. 6. Navigate to Spreading screen and view the "Utilities" dropdown option in left corner and then click it and user can see the "Load spread" option and click it. 7. Load spread popup should get opened with all details. 8. Verify that the user can edit the data in previous spread when view from Load spreads. Enter manual values and save. | E44: The user should be able to enter manual enteries and save data. | F44: Pending
B45: Excl_036 | C45: Spreading screen - Load Spreads | D45: 1. Log in and navigate to the Dashboard page. 2. On the Dashboard page, click the Spreading tab and verify that the "Create Customer" text link is visible. 3. Click "Create Customer", enter the required details, and click Create. 4. On the Customer screen, verify that the "Add Item" button is visible and click it. 5. On the Add Item screen, upload the Excel file and enter values in all mandatory fields. 6. Navigate to Spreading screen and view the "Utilities" dropdown option in left corner and then click it and user can see the "Load spread" option and click it. 7. Load spread popup should get opened with all details. 8. Verify edit is enabled for 5 items only, even when load maximum items. | E45: Edit should be availabel for 5 previous spreads, and current & base. | F45: Pending
B46: Excl_037 | C46: Spreading screen - Load Spreads | D46: 1. Log in and navigate to the Dashboard page. 2. On the Dashboard page, click the Spreading tab and verify that the "Create Customer" text link is visible. 3. Click "Create Customer", enter the required details, and click Create. 4. On the Customer screen, verify that the "Add Item" button is visible and click it. 5. On the Add Item screen, upload the Excel file and enter values in all mandatory fields. 6. Navigate to Spreading screen and view the "Utilities" dropdown option in left corner and then click it and user can see the "Load spread" option and click it. 7. Load spread popup should get opened with all details. 8. Verify that once user make changes in previous spread, submit spread should work in current spread. 9. Launch the spread where changes were made, and verify updated data. | E46: The user should be able to submit spread. Changes should be reflected in the updated spread. | F46: Pending
B47: Excl_038 | C47: Spreading screen - Load Spreads | D47: 1. Log in and navigate to the Dashboard page. 2. On the Dashboard page, click the Spreading tab and verify that the "Create Customer" text link is visible. 3. Click "Create Customer", enter the required details, and click Create. 4. On the Customer screen, verify that the "Add Item" button is visible and click it. 5. On the Add Item screen, upload the Excel file and enter values in all mandatory fields. 6. Navigate to Spreading screen and view the "Utilities" dropdown option in left corner and then click it and user can see the "Load spread" option and click it. 7. Load spread popup should get opened with all details. 8. Verify that when edit the previous spread and cancel/discard the changes, system should not reflect changes in original spread. | E47: Discard should work properly without breaking. | F47: Pending
B48: Excl_039 | C48: Spreading screen - Unit Scale | D48: Verify unit scale functionality by selecting any cell in the current column of the model and clicking any option available under Unit Scale button in the ribbon. The selected option should get applied to all those cells in which value can be mapped (cells with value as data type). | E48: Selected Unit Scale value should get applied to all value cells of the model. | F48: Pending
B49: Excl_040 | C49: Spreading screen - Conversion | D49: Verify Conversion functionality by selecting any cell in the current column of the model and clicking any option available under Conversion button in the ribbon. The selected option should get applied to the selected cell. | E49: Selected conversion value should get applied to the active cell of the model. | F49: Pending
... B107: Excl_098 | C107: Validations Modify | D107: Go to Spreading screen>Modify any validation formula. Add some number with + operator. Then Remove it > observe once validation is TRUE>Submit spread. | E107: The user should be allowed to Modify validation. Number should be added and deleted. The user should be able to submit spread. | F107: Pending
B108: Excl_099 | C108: Expression | D108: Spreading screen>map values (A+B+C). Click + operator and replace with conversion (Divide by 100). Review expression. | E108: Expression should be A/100+B+C. | F108: Pending | H108: Issue still exists.
B109: Excl_100 | C109: Disabled Ribbon Button | D109: In Spreading screen>verify all the disabled button in various conditions, like autofill all, current, all keywords. Error logs etc. Try to click disabled buttons > observe. | E109: The user should not be able to click on disabled button. Disable icon should appear and nothing should happen. | F109: Pending
B110: Excl_101 | C110: Duplicate Model Account | D110: Spreading screen>right-click to insert new row. Add duplicate model account. Review message and click ok. | E110: Insert row popup window should show message saying, similar account already exist, clicking OK will create duplicate account. On clicking OK, model account should be added. | F110: Pending
B111: Excl_102 | C111: Submit Spread-Manual Values | D111: Spreading screen>Map few values. Enter manual value in any cell. Submit spread. | E111: The user should be able to submit spread with manual value only. | F111: Pending
B112: Excl_103 | C112: Submit Spread-Manual String Value | D112: Spreading screen>Map few values. Right click to insert new row. Add String type row. Enter manual value > submit spread. | E112: The user should be able to submit spread with Manual string data. | F112: Pending

Sheet Clean PDF
B2: Test Case Summary
B3: Total Test Cases | D3: =SUM(D4:D8) | E3: Executed Tests | F3: Total Tests | G3: Automation Scripts
B4: Passed | D4: =COUNTIF(F9:F123,"Passed") | E4: =IF(D4=0,,(D4/(D4+D5))) | F4: =IF(D3=0,,(D4/D3)) | G4: =COUNTIF(H10:H493,"Done")
B5: Failed | D5: =COUNTIF(F9:F123,"Failed") | E5: =IF(D5=0,,(D5/(D5+D6))) | F5: =IF(D3=0,,(D5/D3)) | G5: =COUNTIF(H10:H493,"Failed")
B6: Blocked | D6: =COUNTIF(F9:F123,"Blocked") | E6: =IF(D6=0,,(D6/(D6+D7))) | F6: =IF(D3=0,,(D6/D3)) | G6: =COUNTIF(H10:H493,"Blocked")
B7: Pending | D7: =COUNTIF(F9:F1500,"Pending") | E7: =IF(D7=0,,(D7/(D7+D8))) | F7: =IF(D3=0,,(D7/D3)) | G7: =COUNTIF(H10:H493,"Pending")
B8: Not Applicable | D8: =COUNTIF(F9:F123,"Not Applicable") | E8: =IF(D8=0,,(D8/(D8+#REF!))) | F8: =IF(D3=0,,(D8/D3)) | G8: =COUNTIF(H10:H493,"Out of Scope")
B9: S.No. | C9: Module/Sub-Module | D9: Test Steps | E9: Expected Results | F9: Result | G9: Bug ID | H9: Automation Status | I9: Mapped Scripts | J9: Comments
B10: Clean_001 | C10: Clean PDF | D10: Enter the application URL. | E10: Application should be open. | F10: Pending | H10: Done
B11: Clean_002 | C11: Clean PDF | D11: Enter valid credentials and click Login. | E11: User will be successfully logged in to the application. | F11: Pending | H11: Done
B12: Clean_003 | C12: Clean PDF | D12: Click the register now button. | E12: Registration screen should be open. | F12: Pending | H12: Done
B13: Clean_004 | C13: Clean PDF | D13: Enter the required data on registration form and click register button. | E13: The user should be successfully registered and after approval able to login with the credential. | F13: Pending | H13: Done
B14: Clean_005 | C14: Clean PDF | D14: Click Create Customer under Spreading tab. | E14: Create Customer page should be displayed. | F14: Pending | H14: Done
B15: Clean_006 | C15: Clean PDF | D15: Add all the required field on the page and click submit. | E15: Customer created successfully message should display. | F15: Pending | H15: Done
B16: Clean_007 | C16: Clean PDF | D16: Click Add Item under action tab. | E16: Add new item page should display. | F16: Pending | H16: Done
B17: Clean_008 | C17: Clean PDF | D17: Add file from File Store or local and click Add Item. | E17: Item should be created and redirect to the line item page. | F17: Pending | H17: Done
B18: Clean_009 | C18: Clean PDF | D18: Click the spread button under action tab. | E18: Spreading screen should be displayed. | F18: Pending | H18: Done
B19: Clean_010 | C19: Clean PDF | D19: Click the spreading button. | E19: Spreading screen should displayed. | F19: Pending | H19: Done
B20: Clean_011 | C20: Clean PDF | D20: Open the Spreading screen and view the "Secondary Category" in document side and click it. Review the "Clean File" dropdown option and click it. | E20: Water mark and despeckle button should not be there and "Clean file" button should be there under Secondary Category. | F20: Pending | H20: Done
B21: Clean_012 | C21: Clean PDF | D21: Open the Spreading screen and view the "Secondary Category" in document side and click it. Review the "Clean File" dropdown option and click it. | E21: It should display options to reset dropdown or enable the feature. | F21: Pending | H21: Done
... B34: Clean_025 | C34: Clean PDF | D34: User selects cancel. | E34: Pop-up will be closed and it will not affect anything on Spreading screen. | F34: Pending | H34: Done
B35: Clean_026 | C35: Clean PDF | D35: User selects any of the binarization option with No Despeckle, for all pages. | E35: The circle of Clean file will not appear in the Add/Modify item page. The Processed circle will re-start and the status of the item will get changed to Received. Warning message of mapping data and zone loss should also display. | F35: Pending | G35: 71194 | H35: Done
B36: Clean_027 | C36: Clean PDF | D36: Verify that spread button should be disable in Item listing screen until all processes are complete. | E36: Button should be disable due to the processes which got started due to Clean PDF. | F36: Pending | H36: Done
B37: Clean_028 | C37: Clean PDF | D37: Verify that once processes are complete, bulk json will complete and button will get enable to spread. | E37: Spread button should be enabled. | F37: Pending | H37: Done
B38: Clean_029 | C38: Clean PDF | D38: Select all page and click continue. | E38: User move to modify item page. | F38: Pending | H38: Done
B39: Clean_030 | C39: Clean PDF | D39: Click view item list. | E39: Spreading option is disable until all the process is completed. | F39: Pending | H39: Done
B40: Clean_031 | C40: Clean PDF | D40: Multiple file is added for one item>Spreading screen>Select one page from file1>apply all page. | E40: Change should reflect on all file. | F40: Pending | G40: 71197 | H40: Done
B41: Clean_032 | C41: Clean PDF | D41: Draw zones on file2 or file3>Map some values>Select page from file1>apply all page. | E41: Zones and values from all file should wiped. | F41: Pending | H41: Done
B42: Clean_033 | C42: Clean PDF | D42: Modify item>Add one item as image>Select that image > click all page. | E42: Zones and values from all file should wiped. | F42: Pending | H42: Done
B43: Clean_034 | C43: Clean PDF | D43: Make the item as base spread for another item>Go to the item>select all page and continue. | E43: Value of previous spread should autofill after clean and satisfying autofill criteria. | F43: Pending | H43: Done
B44: Clean_035 | C44: Clean PDF | D44: Spread item>Again click Spreading screen>click all page. | E44: System should not allow all option. | F44: Pending | H44: Done
B45: Clean_036 | C45: Clean PDF | D45: Submit to QC>Select for all page. | E45: System should not allow all option. | F45: Pending | H45: Done
B46: Clean_037 | C46: Clean PDF | D46: User open the Spreading screen. | E46: Spreading screen should be displayed. | F46: Pending | H46: Done
B47: Clean_038 | C47: Clean PDF | D47: Open the Spreading screen and view the "Secondary Category" in document side and click it. Review the "Rotate" button option and click it. | E47: Specific Page should be rotated. | F47: Pending | H47: Done
B48: Clean_039 | C48: Clean PDF | D48: Click the clean file for single page. | E48: File should be cleaned and rotated page should maintain its structure. | F48: Pending | H48: Done
B49: Clean_040 | C49: Clean PDF | D49: Click the Clean all file. | E49: User navigate to modify item screen;. File should be cleaned on basis of choosen choice. | F49: Pending | H49: Done
B50: Clean_041 | C50: Clean PDF | D50: Click rotated page number. | E50: Page should maintain its structure after rotation. | F50: Pending | H50: Done
B51: Clean_042 | C51: Clean PDF | D51: Open the Spreading screen and view the "Secondary Category" in document side and click it. Review the "Merge Page" button option and click it. | E51: Consecutive page should be merged and added to the last of file. | F51: Pending | H51: Done
B52: Clean_043 | C52: Clean PDF | D52: Click the clean single page. | E52: Single page should be cleaned and navigate to Spreading screen. | F52: Pending | H52: Done
... B67: Clean_058 | C67: Clean PDF | D67: User selects specific file with no table detection. Apply celan all(Despeckle,binarization and both)>User move to Spreading screen. | E67: The user should have zones and notes processing predicted from AI/ML. | F67: Pending | H67: Done
B68: Clean_059 | C68: Clean PDF | D68: User selects clean all for a file. Accept the required setting from pop up and continue. User observe file processing,zones extraction and key word processing loader. | E68: 5 Image popup should appear with different option. User navigate to the modify item page. Mentioned loader will start from begining. | F68: Pending | G68: 71196 | H68: Done
B69: Clean_060 | C69: Clean PDF | D69: Open the Spreading screen and apply clean with despeckle. User observe the loader in modify item page. User navigate to the item listing page and again back to modify item page. | E69: Applied setting will be work and user navigate to the modify item page. Clean loader should come and show % in the modify item page. Clean % should be shown to the user. | F69: Pending | H69: Done
B70: Clean_061 | C70: Clean PDF | D70: Open the the Spreading screen. User splits one page into two>. User apply rotate>. User apply merge page. User apply binarization for all file. | E70: Cleaned file should retain split file and rotated file but not merged file. | F70: Pending | H70: Done
B71: Clean_062 | C71: Clean PDF | D71: Open the the Spreading screen. User splits one page into two>. User apply rotate>. User apply merge page. User apply binarization with despeckle for all file. | E71: Cleaned file should retain split file and rotated file but not merged file. | F71: Pending | H71: Done
B72: Clean_063 | C72: Clean PDF | D72: Open the the Spreading screen. User splits one page into two>. User apply rotate>. User apply merge page. User apply despeckle for all file. | E72: Cleaned file should retain split file and rotated file but not merged file. | F72: Pending | H72: Done
B73: Clean_064 | C73: Clean PDF | D73: User apply clean file with despeckle for two file out of 3 in item. | E73: User navigate to modify item screen;. Clean loader will show in two file for which clean applied. | F73: Pending | H73: Done
B74: Clean_065 | C74: Clean PDF | D74: Add 3 item > Spreading >clean all file>select two file out of three > click refresh button. | E74: Updated status should be shown in item listing page. | F74: Pending | H74: Done
B75: Clean_066 | C75: Clean PDF | D75: Click the Clean file>User click the reset for all page. | E75: User navigate to the modify item screen. File should be replaced with original file. | F75: Pending | H75: Done
B76: Clean_067 | C76: Clean PDF | D76: Open the Spreading screen>merge file,rotate file,split file>Clean the file>Reset all. | E76: File should not remember the structure and show original file. | F76: Pending | H76: Done
B77: Clean_068 | C77: Clean PDF | D77: Open the Spreading screen > merge file,rotate file,split file>despeckle all>Reset. | E77: Reset for will bring original file. | F77: Pending | H77: Done
B78: Clean_069 | C78: Clean PDF | D78: Open the Spreading screen>map value from table > save as draft>go to previous page>apply split current page>rotate first page>merge any two page>apply water mark only for all. | E78: Observe after clean> Spreading screen >model side should be blank. | F78: Pending | H78: Done
B79: Clean_070 | C79: Clean PDF | D79: Open the Spreading screen>map value from table > save as draft>go to previous page>apply split current page>rotate first page>merge any two page>apply despeckle and original only for all. | E79: Observe after clean> Spreading screen >model side should be blank. | F79: Pending | H79: Done
B80: Clean_071 | C80: Clean PDF | D80: Open the Spreading screen>map value from table > save as draft>go to previous page>apply split current page>rotate first page>merge any two page>apply despeckle and watermark only for all. | E80: Observe after clean> Spreading screen >model side should be blank. | F80: Pending | H80: Done
... B82: Clean_073 | C82: Reset Merged Pages | D82: Spreading screen>merge any 2 pages. Navigates to last page>clean single page. Verify with: A) No despeckle. B) Low despeckle. C) High despeckle. Reset then after every clean setting applied. | E82: The user should be able to Merge Pages. Clean should be applied using mentioned options. Reset should work for single page once clean applied. Reset should not work once already done. | F82: Pending | H82: Done
B83: Clean_074 | C83: Clean PDF - Special Characters | D83: Table mapping heading have special charcter but while reading these charcters are removed by OCR for e.g hypehn, colon, semi-colon, bractes etc. | E83: Sometimes OCR is unable to read the special character from file heading in mapping values, clean the file and validate special character again. | F83: Pending | G83: New | H83: Out of Scope
B84: Clean_075 | C84: Clean PDF - Font Issue Samples | D84: In Font issues sample files, validate the data mapping before and after cleaning. | E84: After cleaning the file mapping accuracy should get increase. | F84: Pending | G84: New | H84: Out of Scope
B85: Clean_076 | C85: Clean PDF -watermark/Stamp Samples | D85: In Watermark sample files, validate the data mapping data above watermark samples before and after cleaning. | E85: After cleaning the file mapping accuracy should get increase. | F85: Pending | G85: New | H85: Done
B86: Clean_077 | C86: Clean PDF -Skewed Samples | D86: In skewed sample files, validate the data rotation for data above watermark samples before and after cleaning. | E86: After cleaning the file mapping accuracy should get increase. | F86: Pending | G86: New | H86: Done
B87: Clean_078 | C87: Clean PDF -Number Format Issue Samples | D87: In number format issue sample files, validate the mapping of dots, comma, numbers quality for samples before and after cleaning. | E87: After cleaning the file mapping accuracy should get increase. | F87: Pending | G87: New | H87: Done

Sheet Split Pdf
B2: Test Case Summary
B3: Total Test Cases | D3: =SUM(D4:D8) | E3: Executed Tests | F3: Total Tests | G3: Automation Scripts
B4: Passed | D4: =COUNTIF(F9:F135,"Passed") | E4: =IF(D4=0,,(D4/(D4+D5))) | F4: =IF(D3=0,,(D4/D3)) | G4: =COUNTIF(H10:H495,"Done")
B5: Failed | D5: =COUNTIF(F9:F135,"Failed") | E5: =IF(D5=0,,(D5/(D5+D6))) | F5: =IF(D3=0,,(D5/D3)) | G5: =COUNTIF(H10:H495,"Failed")
B6: Blocked | D6: =COUNTIF(F9:F135,"Blocked") | E6: =IF(D6=0,,(D6/(D6+D7))) | F6: =IF(D3=0,,(D6/D3)) | G6: =COUNTIF(H10:H495,"Blocked")
B7: Pending | D7: =COUNTIF(F9:F1500,"Pending") | E7: =IF(D7=0,,(D7/(D7+D8))) | F7: =IF(D3=0,,(D7/D3)) | G7: =COUNTIF(H10:H495,"Pending")
B8: Not Applicable | D8: =COUNTIF(F9:F135,"Not Applicable") | E8: =IF(D8=0,,(D8/(D8+#REF!))) | F8: =IF(D3=0,,(D8/D3)) | G8: =COUNTIF(H10:H495,"Out of Scope")
B9: S.No. | C9: Module/Sub-Module | D9: Test Steps | E9: Expected Results | F9: Result | G9: Bug ID | H9: Automation Status | I9: Mapped Scripts | J9: Comments
B10: Split_001 | C10: Split Ribbon Button | D10: Select any customer with added Item then Navigate to Spreading. Screen (Precondition: attached PDF document should have page in booklet view). | E10: Spreading screen should open. | F10: Pending | H10: Done
B11: Split_002 | C11: Split Ribbon Button | D11: Verify Split button in the Spreading screen ribbon. | E11: Split button should be visible to user. | F11: Pending | H11: Done
B12: Split_003 | C12: Split Ribbon Button | D12: Log in to to Spreadsmart application. | E12: The user should be logged in to Spreadsmart application. | F12: Pending | H12: Done
B13: Split_004 | C13: Split Window Option | D13: Open the Spreading screen. Open the Secondary Category menu in the document pane. Review the available options under Secondary Category. | E13: The Split Window option should be visible when Secondary Category is opened. | F13: Pending | H13: Done
B14: Split_004 | C14: Split Pages Option | D14: Open the Spreading screen. Open the Secondary Category menu in the document pane. Review the available options under Secondary Category. | E14: The Split Pages option should be visible when Secondary Category is opened. | H14: Done
B15: Split_005 | C15: Split Page Option Click Action | D15: Open the Spreading screen. Open the Secondary Category menu in the document pane. Review the available options under Secondary Category. Click Split Pages option. | E15: Clicking Split Pages should open a popup where the user can specify where the page should be split. | F15: Pending | H15: Done
B16: Split_005 | C16: Split Window Option Click Action | D16: Open the Spreading screen. Open the Secondary Category menu in the document pane. Review the available options under Secondary Category. Click Split Window option. | E16: Clicking Split Window should open two separate windows in the document area. | H16: Done
B17: Split_006 | C17: Split Ribbon Button | D17: Open the Spreading screen. Open the Secondary Category menu in the document pane. Click "Split Pages" under Secondary Category. Review the popup that displays the split pages. | E17: Split separator should show in the middle of the booklet view of PDF page. | F17: Pending | H17: Done
B18: Split_007 | C18: Split Ribbon Button | D18: Open the Spreading screen. Open the Secondary Category menu in the document pane. Click "Split Pages" under Secondary Category. Review the popup that displays the split pages. Verify that the user can drag separator towards left or right to. Select pages for split. | E18: The system should allow user to drag left or right to select pages for split. | F18: Pending | H18: Out of Scope
B19: Split_008 | C19: Split Ribbon Button | D19: Verify system should not stop user anywhere in the page even if separator crossing the text word on the page. | E19: System should not stop split separator operation even if it is crossing the text/word on the booklet view of the PDF page (Selecting page section for split is completely under user control). | F19: Pending | H19: Out of Scope
B20: Split_009 | C20: Split Ribbon Button | D20: Open the Spreading screen. Open the Secondary Category menu in the document pane. Click "Split Pages" under Secondary Category. Review the popup that displays the split pages. Verify Accept and Cancel button on split page screen. | E20: Accept and Cancel button should be present. | F20: Pending | H20: Done
B21: Split_010 | C21: Split Ribbon Button | D21: Open the Spreading screen. Open the Secondary Category menu in the document pane. Click "Split Pages" under Secondary Category. Review the popup that displays the split pages. Review the Accept and Cancel button on split page screen. Select split page and click Cancel button. | E21: On click Cancel button cursor should remain on Split Page. | F21: Pending | H21: Done
B22: Split_011 | C22: Split Ribbon Button | D22: Open the Spreading screen. Open the Secondary Category menu in the document pane. Click "Split Pages" under Secondary Category. Review the popup that displays the split pages. Review the Accept and Cancel button on split page screen. Select page for split and click Accept button. | E22: Upon Clicking on "Accept" button then a warning message will appear stating that "Mapping data including zones from the current page will get lost. Do you want to continue?. | F22: Pending | H22: Done
B23: Split_012 | C23: Split Ribbon Button | D23: Open the Spreading screen. Open the Secondary Category menu in the document pane. Click "Split Pages" under Secondary Category. Review the popup that displays the split pages. Review the Accept and Cancel button on split page screen. Select page for split and click Accept button. Warning message popup appeared and User is click Continue button. | E23: On click continue page should be split and page number should get adjusted automatically. | F23: Pending | H23: Done
B24: Split_013 | C24: Split Ribbon Button | D24: Verify after splitting the page split will happen and if there is any zone or mapping from that page it will be lost. | E24: Zone and mapped data will should not be saved for split page. | F24: Pending | H24: Done
B25: Split_014 | C25: Split Ribbon Button | D25: Verify that after the split, AI/ML-predicted pages shift by one page so that zones on the remaining page are navigated correctly. | E25: The system should adjust the pages so that zones on the remaining page are navigated correctly. | F25: Pending | G25: 71243 | H25: Done
B26: Split_015 | C26: Split Ribbon Button | D26: Verify that the user can Draw Table on split page and map values. | E26: The user should be able to perform all operations on the split page. | F26: Pending | G26: 71247 | H26: Out of Scope
B27: Split_016 | C27: Split Ribbon Button | D27: Verify Contra/merge /rotate operations can be performed on Split Pages. | E27: The system should allow user to perform all operations on split page. | F27: Pending | H27: Done
B28: Split_017 | C28: Split Ribbon Button | D28: Verify that the user can Submit spread after creating Zones and mapping values. | E28: System should allow user to submit spread. | F28: Pending | H28: Done
B29: Split_018 | C29: Split Ribbon Button | D29: User is after split page action and click continue button from warning popup. Open the Spreading screen and view the pages are in split view. Review the Clean file dropdown from Secondary Category and click it. Review the reset option. Verify Reset option should not work once file is split and processed. | E29: Reset option should not work once files is split and processed. | F29: Pending | H29: Done
B30: Split_019 | C30: Split Ribbon Button | D30: Verify how to bring the file back to original state: 1:User can either delete the file or an item to bring back original. File. 2: Can choose to use Merge page functionality Spreading screen under the Secondary Category from document side. | E30: Verify system allows user to delete the Item Or use "Merge Page" operation from Spreading screen to bring back file to original state. | F30: Pending | G30: 70801 | H30: Done
B31: Split_020 | C31: Split Ribbon Button | D31: Attach file from bulk store and navigate to Spreading screen(file should be already split file through OCR processing) Verify system should not shows any booklet view pages in PDF document. | E31: Split function on Spreading screen should be disable. | F31: Pending | H31: Done
B32: Split_021 | C32: Split Ribbon Button | D32: Verify Split check box (Add Item) and Split All/Current page from Spreading screen should be disabled when files(Booklet view page PDF document) uploaded from Bulk and Adhoc screens. | E32: Split check box (Add Item) and Split All/Current page from Spreading screen should be disabled when files(Booklet view page PDF document) uploaded from Bulk and Adhoc screens. | F32: Pending | H32: Done
B33: Split_022 | C33: Split Ribbon Button | D33: Verify if the user has not split the file initially, but then after item has been created he/she wants to modify the file and use split option. | E33: System should allow to split PDF in modify option. | F33: Pending | H33: Done
B34: Split_023 | C34: Split Integration with Rotate | D34: Upload any file in Spreadsmart, save the item, and navigate to the Spreading screen. | E34: The user should be taken to the Spreading screen. | F34: Pending | H34: Done
B35: Split_024 | C35: Split Integration with Rotate | D35: Click rotate page and wait for page to be rotated. | E35: Page should be rotated. | F35: Pending | H35: Done
B36: Split_025 | C36: Split Integration with Rotate | D36: Apply Split on rotated page. | E36: Split should be applied. | F36: Pending | H36: Done
B37: Split_026 | C37: Split Integration with Rotate | D37: Move any other page, apply split on page and then rotate. | E37: Split should be applied and page should be rotated. | F37: Pending | H37: Done
B38: Split_027 | C38: Split Integration with Clean PDF | D38: In Spreading screen>apply Split in any booklet form page. | E38: Split should be applied. | F38: Pending | H38: Done
B39: Split_028 | C39: Split Integration with Clean PDF | D39: Apply Watermark in split page > observe page. | E39: Page should be watermarked. | F39: Pending | H39: Done
B40: Split_029 | C40: Split Integration with Clean PDF | D40: Map values from page to model. | E40: Values should be mapped. | F40: Pending | H40: Done
B41: Split_030 | C41: Split Integration with Clean PDF | D41: Reset Clean PDF > observe. | E41: Should reset the watermark only, split page should remain same. | F41: Pending | H41: Done
B42: Split_031 | C42: Split Integration with Clean PDF | D42: Navigate to any other page>apply clean PDF and then apply split. | E42: The user should be able to apply split on despeckle/watermark page. | F42: Pending | H42: Done
... B73: Split_062 | C73: Split Functionality in Quality Check | D73: Click split page > observe. | E73: Split screen should appear with preview of partitioning,. | F73: Pending | H73: Done
B74: Split_063 | C74: Split Functionality in Quality Check | D74: Adjust partition area and continue. | E74: Split should happen as per selected area. | F74: Pending | H74: Done | I74: Partition Adjust cannot be done using Automation
B75: Split_064 | C75: Split Functionality in Quality Check | D75: Review the page by scrolling left and right, observe page count. | E75: Page should be split and count should be increased by 1. | F75: Pending | H75: Done
B76: Split_065 | C76: Split Functionality in Quality Check | D76: Submit or reject item after split. | E76: The user should be able to submit or reject. | F76: Pending | H76: Done
B77: Split_066 | C77: Split Functionality in Quality Check | D77: Go to non- QC pool and pick any item to spread > observe split button. | E77: Split button should be present in item picked from Non qc pool. | F77: Pending | H77: Done
B78: Split_067 | C78: Split Functionality in Quality Check | D78: Split page and submit spread > observe. | E78: Split should work and spread should be submitted. | F78: Pending | H78: Done
B79: Split_068 | C79: Split Functionality in Quality Check | D79: Navigate to rejected pool>pick any item and spread. | E79: Item should be spread pick from rejected pool. | F79: Pending | H79: Done
B80: Split_069 | C80: Split Functionality in Quality Check | D80: Split any page with mapped values>Observe. | E80: The page should display warning message that mapped data will be lost. | F80: Pending | H80: Done
B81: Split_070 | C81: Split Functionality in Quality Check | D81: Once user click OK>Split should happen. | E81: Split should work. | F81: Pending | H81: Done
B82: Split_071 | C82: Split with Ai Prediction | D82: Launch Spreading screen>AI prediction should be present for keywords. | E82: AI prediction count should be displayed in Navigate Text. | F82: Pending | H82: Done
B83: Split_072 | C83: Split with Ai Prediction | D83: Click AI prediction button>and select any keyword to expand. Review page number for prediction. Split any page present before Predicted page > observe predicted page number after split. | E83: Predicted page count should increase by 1 after split. | F83: Pending | H83: Done
B84: Split_073 | C84: Split with Ai Prediction | D84: Verify Predicted page number after Split in AI Overlay and then navigate to page. | E84: Page should be increased in both the screens. | F84: Pending | H84: Done
B85: Split_074 | C85: Split with Ai Prediction | D85: Map values from AI Prediction>and then split earlier pages. Review Mapped cell >check page number. | E85: Page number should be updated as per the number of Splits applied. Should reflect results in Mapped cells as well. | F85: Pending | H85: Done
B86: Split_075 | C86: Split with Ai Prediction | D86: Navigate to AI predicted values from mapped cell > observe Text should be highlighted in the correct page and sentence. | E86: After split, correct data should be highlighted. | F86: Pending | H86: Done
... B94: Split_083 | C94: Split all Pages | D94: Verify once user select the Split checkbox" This step depends on the development:Verify the user is able to click the file name to preview the file and check if all pages of. The document to decide whether Split operation is required or not.". | E94: Split operation should start "System should automatically split based on height/width of the page with width/2. Logic.((Please note that Selector in the preview page is not possible so the system will automatically split based on height/width of the page with width/2 logic.This logic will based on dev). | F94: Pending | H94: Done
B95: Split_084 | C95: Split all Pages | D95: Verify when user selects Split Page operation before processing of the file, then the file preview will not have search functionality. | E95: Search functionality should not be not available on file preview when user selects split page operation. | F95: Pending | G95: Applicable for scanned files. | H95: Done | J95: search functionality works for all files - Discussed with Neha
B96: Split_085 | C96: Split all Pages | D96: Verify file preview should not have search functionality when user selects the Split checkbox before processing the file(Add Item and navigate to Spreading screen then verify search function). | E96: File should not have search functionality when user selects the split check box before processing the file. | F96: Pending | H96: Done | J96: search functionality works for all files - Discussed with Neha
B97: Split_086 | C97: Split all Pages | D97: Verify user will not allowed to deselect the Split radio button once the file splits and processed. | E97: The user should not be allowed to deselect Split radio button once the file splits and processed. | F97: Pending | H97: Done
B98: Split_087 | C98: Split all Pages | D98: Verify when user selects the split page checkbox after processing document or processing completed then system should display validation message "File will be processed again for Split operation. Do you want to. Continue"" with Cancel and Continue buttons ". | E98: System should display validation message "" " File will be processed again for Split operation. Do you want to continue"" with Cancel and Continue buttons. | F98: Pending | G98: 70797 | H98: Done
B99: Split_088 | C99: Split all Pages | D99: Click Cancel button,Modify Item screen should display. | E99: Modify Item screen should display. | F99: Pending | H99: Done
B100: Split_089 | C100: Split all Pages | D100: Verify On Click Continue on validation message and then Split Processing of the document should start "File will be processed again for Split operation. Do you want to continue"" with Cancel and Continue buttons ". | E100: File should split and allow user to Add Item to the customer. | F100: Pending | G100: 70797 | H100: Done
B101: Split_090 | C101: Split all Pages | D101: Add Item and Navigate to Spreading screen and verify PDF document. "PDF document should not show any booklet view pages". | E101: PDF document should not show any booklet view pages. | F101: Pending | H101: Done
B102: Split_091 | C102: Split all Pages | D102: Perform all basic spread screen operations on PDF document:Autofill/Mapping/Merge/Rotate/all operation /Table identification /Zone Navigation /Drawing table/Conversion/Contra/Mapping/Free Text/Autofill (more steps can be added at the time of testing). | E102: The system should allow user to perform all spreading operations and submit the spread. | F102: Pending | G102: 71243 | H102: Done
B103: Split_092 | C103: Split all Pages | D103: Verify after create item if user has not split the file Initially. | E103: System should allow user to modify the file and allow to use split option again. | F103: Pending | H103: Done
B104: Split_093 | C104: Split all Pages | D104: Verify all existing functionalities are working after split PDF in Spread. | E104: All existing functionalities should work. | F104: Pending | H104: Done
B105: Split_094 | C105: Split all Pages | D105: Verify If item has been submitted even once using Submit, Submit to QC and Submit to RE, then Clean File. Split All should also be disabled on the Modify item screen. | E105: Split option should be disable on Add Item screen once the item has been submitted even once using Submit, Submit to QC and Submit to RE, then Clean File. Split. | F105: Pending | H105: Done
B106: Split_095 | C106: Split all Pages | D106: Upload five pages PDF file(all pages should be in booklet view) and create an item. On Spreading screen option for Split for current page option. | E106: Upon selecting the split page system should split the current page and total number of pages should become 6. | F106: Pending | H106: Done
B107: Split_096 | C107: Split all Pages | D107: After split operation completed, perform the Clean File for all pages. | E107: Upon selecting the clean file operation user will be redirected to the modify item page. | F107: Pending | H107: Done
B108: Split_097 | C108: Split all Pages | D108: Perform the clean file operation navigate to spread screen and verify file page count should have 6 pages. | E108: Spreading screen file should be having 6 pages file. | F108: Pending | H108: Done
B109: Split_098 | C109: Split all Pages | D109: Upload 10 pages PDF file(all pages should be in booklet view) and create an item. On Spreading screen option for Split for all page option. | E109: Upon selecting the split all page operation system should redirect user to the Modify Item screen and Split check should be selected and split operation should be performed. | F109: Pending | H109: Done
B110: Split_099 | C110: Split all Pages | D110: After split operation Open spread screen and verify the total number of pages for the file. | E110: Total number of pages should be 10 in Spreading screen. | F110: Pending | H110: Done
B111: Split_100 | C111: Split all Pages | D111: Now select Clean operation on Spreading screen. | E111: System should redirect to Modify Item screen and perform Clean operation. | F111: Pending | H111: Done
B112: Split_101 | C112: Split all Pages | D112: Perform the clean file operation navigate to spread screen and file should have 10 pages. | E112: Spreading screen file should be having 10 pages file. | F112: Pending | H112: Done
B113: Split_102 | C113: Split all Pages | D113: After current page split Perform Merge operation on page 3 and Rotate operation on page 6 and perform clean file all page operation. | E113: System should remember page number for which merge and rotate is perform while doing clean file operation. | F113: Pending | H113: Done
B114: Split_103 | C114: Split all Pages | D114: Verify is User able to perform split for current page in Spreading screen and came back to Add Item screen and perform Split for all pages. | E114: System should re run the whole split processing for the file: "Repeat above test cases for the flow ". | F114: Pending | H114: Done
... B122: Split_111 | C122: Split all Pages | D122: Spreading screen>Go to any page with table>map values. Split page>go to next page >Map Mode>select text > observe page text. | E122: The user should be able to split. After split, text should be correct for all the pages below. | F122: Pending | H122: Done
B123: Split_112 | C123: Rotate from Bulk Upload | D123: Upload file from Bulk Upload(file should be booklet view page PDF). File should contain rotated pages. After success upload and navigating to spread screen. All pages should be rotated to portrait view. | E123: Auto split and auto rotate are handled from Bulk view screen. | F123: Pending | G123: New | H123: Done
B124: Split_113 | C124: Split Functionality | D124: Upload 3 files having landscape format >Add Item scree. Open the file and validate the page split or not. | E124: Page should be split and display in display properly in Spreading screen. | F124: Pending | G124: New | H124: Done

Sheet Expressions Verification
B2: Test Case Summary
B3: Total Test Cases | D3: =SUM(D4:D8) | E3: Executed Tests | F3: Total Tests | G3: Automation Scripts
B4: Passed | D4: =COUNTIF(F9:F1483,"Passed") | E4: =IF(D4=0,,(D4/(D4+D5))) | F4: =IF(D3=0,,(D4/D3)) | G4: =COUNTIF(H10:H493,"Done")
B5: Failed | D5: =COUNTIF(F9:F1483,"Failed") | E5: =IF(D5=0,,(D5/(D5+D6))) | F5: =IF(D3=0,,(D5/D3)) | G5: =COUNTIF(H10:H493,"Failed")
B6: Blocked | D6: =COUNTIF(F9:F1483,"Blocked") | E6: =IF(D6=0,,(D6/(D6+D7))) | F6: =IF(D3=0,,(D6/D3)) | G6: =COUNTIF(H10:H493,"Blocked")
B7: Pending | D7: =COUNTIF(F9:F1483,"Pending") | E7: =IF(D7=0,,(D7/(D7+D8))) | F7: =IF(D3=0,,(D7/D3)) | G7: =COUNTIF(H10:H493,"Pending")
B8: Not Applicable | D8: =COUNTIF(F9:F133,"Not Applicable") | E8: =IF(D8=0,,(D8/(D8+#REF!))) | F8: =IF(D3=0,,(D8/D3)) | G8: =COUNTIF(H10:H493,"Out of Scope")
B9: S.No. | C9: Module/Sub-Module | D9: Expression | E9: Action | F9: Result | G9: Bug ID | H9: Automation Status | I9: Mapped Scripts | J9: Comments
B10: Expr_001 | C10: Ribbon Button - ABS | D10: ABS(MV1) | E10: Delete the value. | F10: Pending | H10: Done
B11: Expr_002 | C11: Ribbon Button - ABS | D11: ABS(MV1)*conversion 10 | E11: Delete the value. | F11: Pending | H11: Done
B12: Expr_003 | C12: Ribbon Button - ABS | D12: ABS(MV1)*conversion 10 | E12: Delete the value. | F12: Pending | H12: Done
B13: Expr_004 | C13: Ribbon Button - ABS | D13: MV1+MV2+MV3(ABS) | E13: Delete the values one by one. | F13: Pending | H13: Done
B14: Expr_005 | C14: Ribbon Button - ABS | D14: MV1(ABS)+MV2+MV3(ABS) | E14: Delete the values one by one. | F14: Pending | H14: Done
B15: Expr_006 | C15: Ribbon Button - ABS | D15: ABS(MV1*Contra) | E15: Delete the value. | F15: Pending | H15: Done
B16: Expr_007 | C16: Ribbon Button - ABS | D16: ABS(NEG(MV1)) | E16: Delete the value. | F16: Pending | H16: Done
B17: Expr_008 | C17: Ribbon Button - ABS | D17: MV1+ABS(MV2*Conv 10) | E17: Delete the second value first, then delete the next value. | F17: Pending | H17: Done
B18: Expr_009 | C18: Ribbon Button - ABS | D18: MV1+ABS(MV2*Conv 10) | E18: Delete the first value, then delete the next value. | F18: Pending | H18: Done
B19: Expr_010 | C19: Ribbon Button - ABS | D19: ABS(MV1+MV2*MV3/MV4)-MV5-MV6 | E19: Delete the values one by one. | F19: Pending | H19: Done
B20: Expr_011 | C20: Ribbon Button - ABS | D20: MV1+ABS(MV2) | E20: Delete 1st value > observe Both value deleted. | F20: Pending | H20: Done
B21: Expr_012 | C21: Ribbon Button - ABS | D21: ABS((MV1*conv 10)+MV2/conv 10+(MV3*contra)) | E21: Delete values, delete Contra value at the end. | F21: Pending | H21: Done
... B127: Expr_118 | C127: Complex Expressions | D127: (ABS(MV1+MV2*Contra+MV3*Contra))/Conv 100 | E127: Delete the values one by one. | F127: Pending | H127: Done
B128: Expr_119 | C128: Complex Expressions | D128: Spread any item>Map values to model side from Zone 1. Appy Unit scale conversion. Now map values from Zone 2 in the same cells where Unit scale applied. Expression becomes like (V1+V2)*100+V3. Submit and continue spread. Autofill from Zone 1. Apply unit scale. Now autofill from Zone 2. Observe expression is becoming like (V1+V2+V3)*100. | E128: Expression should maintain it's sequence same as base. | F128: Pending | H128: Done | J128: Newly added 3/23/2026
B129: Expr_120 | C129: Complex Expressions | D129: Map value in base V1 and apply Unit scale. Now, map values from other zone in the same cell. Apply ABS>Expression becomes ABS((V1)*100+V2+V3) Submit and continue>Autofill Zone 1 only. Observe Expression is ABS((V1)). Expected: This expression should have single bracket only. Now apply Unit scale. Autofill from Zone 2> Observe Unit scale is applied to whole value now. currently showing (ABS((V1)+V2+V3))*100 | E129: Expression should maintain the sequence. | F129: Pending | H129: Done | J129: Newly added 3/23/2026
B130: Expr_121 | C130: Complex Expressions | D130: Map values from Zone1 and apply Unit scale. Now, map values from Zone1 in the same cell and map some values from Zone2. Expression is (V1 (Z1))*100+V2(Z2)+V3(Z1) Submit and continue>Autofill Zone 1 only. Observe Expression is (V1)+V2 Now apply Unit scale, expression becomes ((V1)+V2)*100. | E130: Expression should maintain the sequence. | F130: Pending | H130: Done | J130: Newly added 3/23/2026
B131: Expr_122 | C131: Complex Expressions | D131: Map values from Zone1 and apply Unit scale. Now, Apply contra Now, map value from Zone2 in the same cell. Expression is ((V1 (Z1))*10)*(-1)+V2(Z2) Submit and continue>Autofill Zone 1 only. Observe Expression is (((V1))*(-1) Now apply Unit scale Autofill from Zone 2> Observe Unit scale is applied to whole value now. expression becomes (((V1))*(-1)+V2)*10 | E131: Expression should maintain the sequence. | F131: Pending | H131: Done | J131: Newly added 3/23/2026
B132: Expr_123 | C132: Complex Expressions | D132: Map values from Zone1 and apply Unit scale. Now, Apply negative Now, map value from Zone2 in the same cell. Expression is NEG((V1 (Z1))*10)+V2(Z2) Submit and continue>Autofill Zone 1 only. Observe Expression is (NEG((V1 (Z1)) Now apply Unit scale Autofill from Zone 2> Observe Unit scale is applied to whole value now. expression becomes (NEG((V1 (Z1))+V2(Z2)*10 | E132: Expression should maintain the sequence. | F132: Pending | H132: Done | J132: Newly added 3/23/2026
B133: Expr_124 | C133: Complex Expressions | D133: Map values from Zone1 and apply Unit scale. Now, Apply Conversion Now, map value from Zone2 in the same cell. Expression is ((V1 (Z1))*10)*100+V2(Z2) Submit and continue>Autofill Zone 1 only. Observe Expression is ((V1(Z1)))*100 Now apply Unit scale Autofill from Zone 2> Observe Unit scale is applied to whole value now. expression becomes (((V1(Z1)))*100+V2(Z2)*10 | E133: Expression should maintain the sequence. | F133: Pending | H133: Done | J133: Newly added 3/23/2026

Sheet Statement Export
B2: Test Case Summary
B3: Total Test Cases | D3: =SUM(D4:D8) | E3: Executed Tests | F3: Total Tests | G3: Automation Scripts
B4: Passed | D4: =COUNTIF(F9:F35,"Passed") | E4: =IF(D4=0,,(D4/(D4+D5))) | F4: =IF(D3=0,,(D4/D3)) | G4: =COUNTIF(H10:H496,"Done")
B5: Failed | D5: =COUNTIF(F9:F89,"Failed") | E5: =IF(D5=0,,(D5/(D5+D6))) | F5: =IF(D3=0,,(D5/D3)) | G5: =COUNTIF(H10:H496,"Failed")
B6: Blocked | D6: =COUNTIF(F9:F89,"Blocked") | E6: =IF(D6=0,,(D6/(D6+D7))) | F6: =IF(D3=0,,(D6/D3)) | G6: =COUNTIF(H10:H496,"Blocked")
B7: Pending | D7: =COUNTIF(F10:F503,"Pending") | E7: =IF(D7=0,,(D7/(D7+D8))) | F7: =IF(D3=0,,(D7/D3)) | G7: =COUNTIF(H10:H496,"Pending")
B8: Not Applicable | D8: =COUNTIF(F9:F89,"Not Applicable") | E8: =IF(D8=0,,(D8/(D8+#REF!))) | F8: =IF(D3=0,,(D8/D3)) | G8: =COUNTIF(H10:H496,"Out of Scope")
B9: S.No. | C9: Module/Sub-Module | D9: Test Steps | E9: Expected Results | F9: Result | G9: Bug ID | H9: Automation Status | I9: Mapped Scripts | J9: Comments
B10: Export_001 | C10: Statement Export | D10: Go to Spreading > Statement Export. Review the UI of export statements page. | E10: The correct UI should be displayed. | F10: Pending | H10: Done
B11: Export_002 | C11: Filters | D11: Check filters present to export. | E11: The page should display following filters: • Model Type. • Status. • Spread Type. • Frequency. • Audit Method. • Date Range (Statement Date). | F11: Pending | H11: Done
B12: Export_003 | C12: Model | D12: Check all mentioned filters. | E12: The control should remain disabled and should only be enabled when model is selected. | F12: Pending | H12: Done
B13: Export_004 | C13: Model | D13: Model type filter should remain enabled. | E13: The user should be able to select model from dropdown. | F13: Pending | H13: Done
B14: Export_005 | C14: Search | D14: Select model and search. | E14: The page should display all customers which have line items in Draft, For QC or spread state and are mapped to selected model. | F14: Pending | H14: Done
B15: Export_006 | C15: Refresh | D15: Search the model and refresh. | E15: Default text should not disappear when user selects any model/filters and clicks on refresh icon. | F15: Pending | H15: Pending
B16: Export_007 | C16: Export | D16: Select single customer and export. | E16: Should export single workbook with the name of the customer and there should be 3 worksheets based on status (Spread, draft or for QC). | F16: Pending | H16: Done
B17: Export_008 | C17: Filters | D17: Select. • Model Type. • Status. • Spread Type. • Frequency. • Audit Method. • Date Range (Statement Date). Select single customer and export. | E17: Should export single workbook with the name of the customer and there should be 3 worksheets based on filters selected. | F17: Pending | H17: Done
B18: Export_009 | C18: Status | D18: Check data of exported file FOR Draft and spread. | E18: The page should display values as saved while spreading. | F18: Pending | H18: Done
B19: Export_010 | C19: Multiple Customers | D19: Select multiple customers and export. | E19: Should export single consolidated workbook with different 3 worksheets for each customer based on status (final, draft or for QC) having name of the customer. | F19: Pending | H19: Done
B20: Export_011 | C20: Order | D20: 1. For same customer submit spreads using same model for multiple years. 2. Export statement for customer. | E20: Should export statement in descending order of year - 2019,2020,2021. | F20: Pending | H20: Done
B21: Export_012 | C21: Order | D21: 1. For same customer submit spreads using same model for same year and same Statement Dates. 2. Export statement for customer. | E21: Should export statement in descending order wrt spread type. Original(last spread), Original,Restated. | F21: Pending | H21: Done
... B43: Export_034 | C43: Export | D43: Click Multiple Customer. | E43: Observe Report CheckBox de select and disabled Automatically. | F43: Pending | H43: Done
B44: Export_035 | C44: Export | D44: User Deselect All customer. | E44: User Observe report check box is eabled but deselected. | F44: Pending | H44: Done | J44: Product Backlog Item 88304

Sheet Model Management
B2: Test Case Summary
B3: Total Test Cases | D3: =SUM(D4:D8) | E3: Executed Tests | F3: Total Tests | G3: Automation Scripts
B4: Passed | D4: =COUNTIF(F9:F103,"Passed") | E4: =IF(D4=0,,(D4/(D4+D5))) | F4: =IF(D3=0,,(D4/D3)) | G4: =COUNTIF(H10:H488,"Done")
B5: Failed | D5: =COUNTIF(F9:F103,"Failed") | E5: =IF(D5=0,,(D5/(D5+D6))) | F5: =IF(D3=0,,(D5/D3)) | G5: =COUNTIF(H10:H488,"Failed")
B6: Blocked | D6: =COUNTIF(F9:F103,"Blocked") | E6: =IF(D6=0,,(D6/(D6+D7))) | F6: =IF(D3=0,,(D6/D3)) | G6: =COUNTIF(H10:H488,"Blocked")
B7: Pending | D7: =COUNTIF(F9:F500,"Pending") | E7: =IF(D7=0,,(D7/(D7+D8))) | F7: =IF(D3=0,,(D7/D3)) | G7: =COUNTIF(H10:H488,"Pending")
B8: Not Applicable | D8: =COUNTIF(F9:F103,"Not Applicable") | E8: =IF(D8=0,,(D8/(D8+#REF!))) | F8: =IF(D3=0,,(D8/D3)) | G8: =COUNTIF(H10:H488,"Out of Scope")
B9: S.No. | C9: Module/Sub-Module | D9: Test Steps | E9: Expected Results | F9: Result | G9: Bug ID | H9: Automation Status | I9: Mapped Scripts | J9: Comments
B10: Model_001 | C10: Create Model | D10: Log in to SS as Manager>Spreading. Models>click create Model. | E10: Create Model screen should be launched. | F10: Pending | H10: Done
B11: Model_002 | C11: Create Model | D11: Log in to SS as Analyst>Spreading. Models>Observe Create model button should not be present. Only Existing models menu should be there. | E11: Analyst should not have access to create model. | F11: Pending | H11: Done
B12: Model_003 | C12: Create Model | D12: Verify that the user can add the new Model. User will redirect to create model and see option: Format painter. Border style. Validation. Formula. Clear format. Clear all. Font size. Text format. Text colour. Fill colour. Group Row. Ungroup Row. Conditional formatting and. Save Model. | E12: Mentioned options should be present in Model screen. | F12: Pending | H12: Done
B13: Model_004 | C13: Create Model | D13: Verify that the user can see the excel model page with below column name: Account. Type. Formula. Data Type. Data Length. Shortcut. Unit scale conversion. | E13: Mentioned options should be present in Model screen. | F13: Pending | H13: Done
B14: Model_005 | C14: Create Model | D14: Verify filling details while creating new model: Account. Type. Formulas. Data Type - Will be default as numeric, in case string is required customer to inform. Data length - Zero to be default but editable option. Shortcut - Only Category rows to be allowed as yes others to be as No. Unit Scale Conversion - Validations, formulas, Category rows and empty rows to be default as No. Value rows to be default as Yes - with option to be editable. Formatting option on top to be restricted for the users except wrap text, group, ungroup and save. Save option to be available for addition or changes done for Unit Scale and Decimal places. | E14: The user should be able to fill details and create model. | F14: Pending | H14: Done
B15: Model_006 | C15: Create Model | D15: Verify that while saving a model, user should be asked for Model name, Taxonomy Group and Group. | E15: The user should be able to select all the asked details and save model after filling the details only. | F15: Pending | H15: Done
B16: Model_007 | C16: Existing Model | D16: Log in to Spreadsmart as Analyst>. Navigate to Existing Models page by clicking Existing Models sub menu under Spreading menu. | E16: Existing models page will be displayed. | F16: Pending | H16: Done
B17: Model_008 | C17: Existing Models | D17: Verify that model list screen show below options: Model Name. Creation Date. Last modified date. Created By. Modified By. Groups mapped. Taxonomy groups mapped. Status. Action. | E17: Mentioned columns should be present in Model list screen. | F17: Pending | H17: Done
B18: Model_009 | C18: Modify Model | D18: Verify that the user can modify existing model by click model or Modify button in action and should update data. Account. Type. Formulas. Data Type - Will be default as numeric, in case string is required customer to inform. Data length - Zero to be default but editable option. Shortcut - Only Category rows to be allowed as yes others to be as No. Unit Scale Conversion - Validations, formulas, Category rows and empty rows to be default as No. Value rows to be default as Yes - with option to be editable. Formatting option on top to be restricted for the users except wrap text, group, ungroup and save. Save option to be available for addition or changes done for Unit Scale and Decimal places. Validations to be shown on top of the model, but that part to be default open as 'Grouped' always. Only user can ungroup in Spreading screen if required. | E18: The user should be able to modify data which is editable. | F18: Pending | H18: Done
B19: Model_010 | C19: Add Template | D19: Verify that the user can Add template by click Add template option under Actions button. 1. Add template using Pdf. 2. Upload by Taxonomy. | E19: The user should be able to add template. | F19: Pending | H19: Done
B20: Model_011 | C20: Add Template | D20: 1. User should be able to upload PDF and submit. 2. Verify that Upload by Taxonomy option should navigate to Taxonomy screen and user able to select zones and keywords. | E20: The user should be able to add template using mentioned options. | F20: Pending | H20: Done
B21: Model_012 | C21: Modify Template | D21: Verify that after adding template Modify template option is present instead of Add template. Modify template should show the same screen as Add template screen. | E21: Modify template should replace the existingtemplate with new. | F21: Pending | H21: Done
... B31: Model_022 | C31: Clone Model | D31: Verify that the user can create a copy of model by click Clone model. | E31: Clone model should work as mentioned. | F31: Pending | H31: Done
B32: Model_023 | C32: Copy Template | D32: Verify copy template button when model is cloned with same group and taxonomy group. Add/modify template > observe copy existing template button. Select Model name and set template name and save. | E32: Copy existing template button should only come when group and taxonomy groups are same. The user should be able to copy template from existing. Template should be directly configured. | F32: Pending | G32: Applicable in CL only. | H32: Done
B33: Model_024 | C33: Export | D33: Verify that the user can export Model into excel by click Export option in Action button. | E33: Model should be exported into excel. | F33: Pending | H33: Done
B34: Model_025 | C34: Active | D34: Verify that the user can Active/inactive the model. | E34: Active/Inactive should work. | F34: Pending | H34: Done
B35: Model_026 | C35: Filters | D35: Verify that the user can filter customer using the filters present in Existing Models screen. Apply Last Modified Date Range. Select Access group(s). | E35: The user should be able to search by used filters. | F35: Pending | H35: Done
B36: Model_027 | C36: Search | D36: Verify that the user can Search by Model Name. | E36: The user should be able to search. | F36: Pending | H36: Done
B37: Model_028 | C37: Reset | D37: Verify that the user can reset the filters applied, by click Reset button. | E37: Reset should work. | F37: Pending | H37: Done
B38: Model_029 | C38: Clone Model | D38: Clone any existing model>any modify the line items. Add template>view modified line items. Map values and submit spread. | E38: The user should be able to clone model and edit line items. Mapping should be done and submitted in template. | F38: Pending | H38: Done
B39: Model_030 | C39: Template Modify | D39: Precondition: Template should be configured in a model. 1. Update complete taxonomy list, replace existing keywords with new. 2. Modify Template>select keywords, zones>create template. 3. Configure Template again. | E39: The user should be able to replace keywords. While modifying, keywords should not be duplicated. Template should be configured with updated keywords. | F39: Pending | H39: Done
B40: Model_031 | C40: Template Modify - Free Text Checkbox | D40: Precondition: Free text checkbox unchecked. Search keyword > reset>search again>select zones>create template>. Navigate to template configuration screen > observe all keywords and last page. Precondition: Free text checkbox checked. Search keyword > reset>search again>select zones>create template>. Navigate to template configuration screen > observe all keywords and last page. | E40: Case 1: Template should be created with all the selected keywords and last page should have free text keywords. Case2: Template should be created with all the selected keywords without any free text page. | F40: Pending | H40: Done
B41: Model_032 | C41: Template Keyword Search | D41: Select any Model > click Add template. Create using Taxonomy>using existing template. Search keyword>cancel>modify template again>search keyword. Add Zone>create template. | E41: Template should be created with all the selected keywords. | F41: Pending | H41: Done
B42: Model_033 | C42: Large Model | D42: Verify creating a Model up to 3000 lines/accounts. Modify model and update line items. | E42: The user should be able to create large model and modify as well. | F42: Pending | H42: Done
B43: Model_034 | C43: Large Model | D43: Configure template in large model and launch in Spreading screen. | E43: Large model should be launched wih template as a base in Spreading screen. | F43: Pending | H43: Done
B44: Model_035 | C44: Modify Model | D44: Verify modifying line items for a Model which is already in use. | E44: The user should only be allowed add new line item. Existing accounts cannot be modified and deleted. | F44: Pending | H44: Done
... B46: Model_037 | C46: Line Item | D46: Create model>enter 301 characters in line item>enter. Once user click another cell>user should get error message saying more than 300 characters not allowed. Once user removes one character>error should no more come. | E46: Error should be displayed. Error should be resolved once character count matches the limit. | F46: Pending | H46: Done
B47: Model_038 | C47: Role Based Permission- Admin | D47: Login with Admin. Go to Existing Models. Review New Model button and Create Model menu. Select any existing model and try to Modify. | E47: The user should be able to Login with Admin. Create Model button should visible. New Model button in existing model screen should be enabled. And, user should be able to Modify existing models. | F47: Pending | G47: Newly Added | H47: Pending | I47: 1
B48: Model_039 | C48: Role Based Permission- Global Manager | D48: Login with Global Manager role. Go to Existing Models. Review New Model button and Create Model menu. Select any existing model and try to Modify. Try to Active/Inactive Model. | E48: The user should be able to Login with Global Manager. Create Model button should be hidden. New Model button in existing model screen should be disabled. And, user should not be able to Modify existing models. The user should be able to Active/Inactive the model. | F48: Pending | G48: Newly Added | H48: Pending | I48: 1
B49: Model_040 | C49: Role Based Permission- Manager | D49: Login with Manager role. Go to Existing Models. Review New Model button and Create Model menu. Select any existing model and try to Modify. Try to Active/Inactive Model. | E49: The user should be able to Login with Manager. Create Model button should visible. New Model button in existing model screen should be enabled. And, user should be able to Modify existing models. The user should be able to Active/Inactive the model. | F49: Pending | G49: Newly Added | H49: Pending | I49: 1
B50: Model_041 | C50: Role Based Permission- Analyst | D50: Login with Analyst role. Go to Existing Models. Review New Model button and Create Model menu. Select any existing model and try to Modify. Try to Active/Inactive Model. | E50: The user should be able to Login with Analyst. Create Model button should be hidden. New Model button in existing model screen should be disabled. And, user should not be able to Modify existing models. The user should not have permission to Active/Inactive the model. | F50: Pending | G50: Newly Added | H50: Pending | I50: 1
B51: Model_042 | C51: Insert Row in Bottom | D51: Create model screen>Paste rows more than 200. Review last row is showing blank. Right click to insert new row above/below. Enter data and save model. | E51: The user should be able to insert new row above or below. Model should be save with newly added row. | F51: Pending | G51: Newly Added | H51: Pending | I51: 1
B52: Model_043 | C52: Validations | D52: While creating model, provide reference of blank cell in validation formula. Save model > observe. | E52: The user should not be able to save model with blank cell as validation reference. | F52: Pending | G52: Newly Added | H52: Pending | I52: 0.5
B53: Model_044 | C53: Formulas | D53: While creating model, provide reference of blank cell in formula. Save model > observe. | E53: The user should not be able to save model with blank cell as formula reference. | F53: Pending | G53: Newly Added | H53: Pending | I53: 0.5
B54: Model_045 | C54: Insert Row Above | D54: Create New model>right-click and click Insert row above. Enter the account name and save the model. Launch any existing model>Right click and click Insert row above. Enter the account name and save the model. Modify any model for which item already submitted. Right click and click Insert row above. Enter the account name and save the model. | E54: The user should be able to insert new row in all 3 cases. | F54: Pending | H54: Pending | I54: 1
B55: Model_046 | C55: Insert Row Below | D55: Create New model>right-click and click Insert row below. Enter the account name and save the model. Launch any existing model>Right click and click Insert row below. Enter the account name and save the model. Modify any model for which item already submitted. Right click and click Insert row below. Enter the account name and save the model. | E55: The user should be able to insert new row in all 3 cases. | F55: Pending | H55: Pending | I55: 1
B56: Model_047 | C56: Delete Row | D56: Create New model>right-click and click Insert row below. Enter account name>Right click again and click Delete row. Launch any existing model (Not used in any item)>Right click and click Delete row > save model. Modify any model for which item already submitted. Right click and click Delete row > observe. | E56: 1. The user should be able to insert and delete added row. 2. The user should be able to delete added row from saved model. 3. Delete row option should be disabled. | F56: Pending | H56: Pending | I56: 1
B57: Model_048 | C57: Hide Row | D57: Create New model>Add few rows. Right click again and click Hide row. Launch any existing model (Not used in any item)>Right click and click Hide row > save model. Modify any model for which item already submitted. Right click and click Hide row > observe. | E57: The user should be able to hide select rows in mentioned cases. | F57: Pending | H57: Pending | I57: 1
B58: Model_049 | C58: Unhide Row | D58: Create New model>Add few rows. Right click again and click Unhide row. Launch any existing model (Not used in any item)>Right click and click Unhide row > save model. Modify any model for which item already submitted. Right click and click Unhide row > observe. | E58: The user should be able to Unhide select rows in mentioned cases. | F58: Pending | H58: Pending | I58: 1
B59: Model_050 | C59: Group Rows | D59: Create New model>Add few rows. Select a range of rows. Right click again and click Group rows. Verify without selection of multiple row. Right click and click Group rows. Verify click Group row ribbon button when range of rows is not selected. | E59: The user should be able to group the rows. | F59: Pending | H59: Pending | I59: 1
B60: Model_051 | C60: Ungroup Rows | D60: Select any of grouped rows. Right click and click Ungroup rows. Verify without selection of multiple row. Right click and click Group rows. Verify click Group row ribbon button when range of rows is not selected>should show validation message to select range of rows. | E60: Rows should be ungrouped. | F60: Pending | H60: Pending | I60: 1
B61: Model_052 | C61: Template Configuration | D61: Create expression in template as: ABS(1+1+1)/10. Delete all values from Mapped cell popup. | E61: The user should be able to delete all the values. | F61: Pending | H61: Pending | I61: 1

Sheet  Bulk Upload
B2: Test Case Summary
B3: Total Test Cases | D3: =SUM(D4:D8) | E3: Executed Tests | F3: Total Tests | G3: Automation Scripts
B4: Passed | D4: =COUNTIF(F9:F35,"Passed") | E4: =IF(D4=0,,(D4/(D4+D5))) | F4: =IF(D3=0,,(D4/D3)) | G4: =COUNTIF(H10:H493,"Done")
B5: Failed | D5: =COUNTIF(F9:F141,"Failed") | E5: =IF(D5=0,,(D5/(D5+D6))) | F5: =IF(D3=0,,(D5/D3)) | G5: =COUNTIF(H10:H493,"Failed")
B6: Blocked | D6: =COUNTIF(F9:F141,"Blocked") | E6: =IF(D6=0,,(D6/(D6+D7))) | F6: =IF(D3=0,,(D6/D3)) | G6: =COUNTIF(H10:H493,"Blocked")
B7: Pending | D7: =COUNTIF(F9:F141,"Pending") | E7: =IF(D7=0,,(D7/(D7+D8))) | F7: =IF(D3=0,,(D7/D3)) | G7: =COUNTIF(H10:H493,"Pending")
B8: Not Applicable | D8: =COUNTIF(F9:F141,"Not Applicable") | E8: =IF(D8=0,,(D8/(D8+#REF!))) | F8: =IF(D3=0,,(D8/D3)) | G8: =COUNTIF(H10:H493,"Out of Scope")
B9: S.No. | C9: Module/Sub-Module | D9: Test Steps | E9: Expected Results | F9: Result | G9: Bug ID | H9: Automation Status | I9: Mapped Scripts | J9: Comments
B10: Bulk_001 | C10: Bulk Upload | D10: Click Spreading>View Status/Upload File. Review screen. | E10: The screen should open correctly. | F10: Pending | H10: Pending | I10: 0.25
B11: Bulk_002 | C11: All Tabs | D11: Once user is on View Status/Upload File Screen > observe tabs present in screen should be as below. My Files. All Files. Error Files. | E11: All tabs should be displayed on the screen. | F11: Pending | H11: Pending | I11: 0.25
B12: Bulk_003 | C12: Switch Tabs | D12: Switch between all available tabs and review the data shown in each tab, if present. | E12: The user should be able to switch between the tabs. | F12: Pending | H12: Pending | I12: 0.25
B13: Bulk_004 | C13: Search File | D13: Review Search tab present in screen. Enter text in search tab and view results. Enter text with no files uploaded>enter and observe. | E13: The user should be able to search available files. If the user searches for files that are not present, a "No records found" message should be displayed. | F13: Pending | H13: Pending | I13: 0.5
B14: Bulk_005 | C14: Remove Search Text | D14: Remove the search text from the text box and review the screen. | E14: The screen should display the My Files tab. | F14: Pending | H14: Pending | I14: 0.5
B15: Bulk_006 | C15: Language Dropdown | D15: Review Select Language button on top of the page. Click dropdown > observe list of languages. | E15: Select language dropdown should show list of all the active languages present in Language management screen. | F15: Pending | H15: Pending | I15: 0.5
B16: Bulk_007 | C16: Choose Button | D16: Review Choose button on screen with text on left "Maximum size allowed for selected files is 1 GB.". | E16: Choose button should be present with the mentioned text. | F16: Pending | H16: Pending | I16: 0.5
B17: Bulk_008 | C17: Upload File | D17: Select any language from dropdown > click choose button. And select file from system to upload. View My files tab then. | E17: The user should be able to upload file and file should be visible in My files tab. | F17: Pending | H17: Pending | I17: 0.5
B18: Bulk_009 | C18: Bulk Upload- My Files | D18: Upload at least 10 files at a time > observe sequence of files in My files tab. | E18: All files should be uploaded successfully, and the latest file should be displayed at the top of the list. | F18: Pending | H18: Pending | I18: 0.5
B19: Bulk_010 | C19: Bulk Upload- all Files | D19: Verify files uploaded from the logged in user in All files tab. | E19: Files should be visible in All files tab. | F19: Pending | H19: Pending | I19: 0.5
B20: Bulk_011 | C20: Bulk Upload- all Files | D20: Verify that the All Files tab displays files uploaded by other users in the same access group. | E20: All files belonging to the same access group should be visible in the All Files tab. | F20: Pending | H20: Pending | I20: 0.5
B21: Bulk_012 | C21: Bulk Upload- Error Files | D21: Click the error files tab. | E21: Error file should be shown to the user. | F21: Pending | H21: Pending | I21: 0.5
... B36: Bulk_027 | C36: Bulk Upload | D36: Upload all files, images, document, PDF, excels each type at least 20 at a time. | E36: The user should be able to upload files. | F36: Pending | H36: Pending | I36: 1
B37: Bulk_028 | C37: Bulk Upload | D37: Upload file and validate the time taken for completing process, also validate the language dropdown. | E37: Upload file should not take much time to upload and processing of file should be done only if language is present. | F37: Pending | G37: New | H37: Pending | I37: 1
B38: Bulk_029 | C38: Bulk Upload- Error File | D38: Upload a file without selecting a language, then correct the language. | E38: Once the error is removed from the file, processing should continue successfully. | F38: Pending | G38: New | H38: Pending | I38: 1
B39: Bulk_030 | C39: Bulk Upload | D39: Upload files in different languages such as English, Arabic, Chinese, Russian, and Spanish. | E39: All files should be uploaded successfully, and the latest file should be displayed at the top of the list. | F39: Pending | G39: New | H39: Pending | I39: 1
B41: 1 | C41: Bulk Upload - pagination | D41: Log in to the URL: | E41: Pagination should work correctly. | F41: 138370-ID
D42: https://ssdevwebapps.evalueserve.com/qaq323/mapCustomer/BulkUpload
D43: Go to the Spreading tab.
D44: Go to the bulk upload screen.
D45: When landed on the page pagination is showing.
D46: When we upload new item and refresh the screen once or twice it is showing only page after multiple files is there.
B47: 2 | C47: Bulk Upload_ Failing Zone Extraction | D47: Log in to the URL: | E47: Zone extraction should work correctly. | F47: 139096-ID
D48: https://ssdevwebapps.evalueserve.com/uatq323/item
D49: Go to the Spreading tab.
D50: Go to the Existing Customer screen.
D51: Go to the Add Item.
D52: Observed this issue.
D53: Same issue observed when we add the item though bulk upload screen.

Sheet Reporting
B2: Test Case Summary
B3: Total Test Cases | D3: =SUM(D4:D8) | E3: Executed Tests | F3: Total Tests | G3: Automation Scripts
B4: Passed | D4: =COUNTIF(G10:G500,"Passed") | E4: =IF(D4=0,,(D4/(D4+D5))) | F4: =IF(D3=0,,(D4/D3)) | G4: =COUNTIF(I10:I500,"Done")
B5: Failed | D5: =COUNTIF(G10:G198,"Failed") | E5: =IF(D5=0,,(D5/(D5+D6))) | F5: =IF(D3=0,,(D5/D3)) | G5: =COUNTIF(I10:I500,"Failed")
B6: Blocked | D6: =COUNTIF(G10:G198,"Blocked") | E6: =IF(D6=0,,(D6/(D6+D7))) | F6: =IF(D3=0,,(D6/D3)) | G6: =COUNTIF(I10:I500,"Blocked")
B7: Pending | D7: =COUNTIF(G10:G500,"Pending") | E7: =IF(D7=0,,(D7/(D7+D8))) | F7: =IF(D3=0,,(D7/D3)) | G7: =COUNTIF(I10:I500,"Pending")
B8: Not Applicable | D8: =COUNTIF(G10:G198,"Not Applicable") | E8: =IF(D8=0,,(D8/(D8+#REF!))) | F8: =IF(D3=0,,(D8/D3)) | G8: =COUNTIF(I10:I500,"Out of Scope")
B9: S.No. | C9: Module/Sub-Module | D9: Test Scenario | E9: Test Steps | F9: Expected Results | G9: Result | H9: Bug ID | I9: Automation Status | J9: Mapped Scripts | K9: Comments
B10: Report_001 | C10: Reporting page Dashboard | D10: Validate Reporting page. | E10: 1. Log in to the Spreadsmart application. 2. Click Reporting in the page header. | F10: The user should be taken to the Reporting page, "Report - Spreading Details". | G10: Pending | I10: Done
B11: Report_002 | C11: Reporting page Dashboard | D11: Validate the default view of the Reporting page. | E11: 1. Log in to the Spreadsmart application. 2. Click Reporting in the page header. | F11: "Spreading Details" page should be the default page appearing on clicking Reporting. | G11: Pending | I11: Done
B12: Report_003 | C12: Reporting page Dashboard | D12: Validate the components of Reporting page. | E12: 1. Log in to the Spreadsmart application. 2. Click Reporting in the page header. | F12: Reporting page consist of the following Report List dropdown. 1. Spreading tab. 2. Audit Log tab. 3. Covenant tab. 4. Technical Exception tab. 5. Format type radio buttons. 7. Information button. 8. Refresh button. 9. Generate Report button. | G12: Pending | I12: Done
B13: Report_004 | C13: Reporting > Spreading tab | D13: Validate the sub tabs under "Spreading" tab dropdown. | E13: 1. Log in to the Spreadsmart application. 2. Click Reporting in the page header. 3. Click the Spreading tab dropdown under Report List. 4. Validate the sub tabs. | F13: Spreading tab should have the following clickable sub tabs. 1. Spreading Details. 2. Customer Details. 3. User Details. 4. OCR Usage. 5. Global Taxonomy Download. 6. Customer Taxonomy Download. 7. Document Quality. | G13: Pending | I13: Done
B14: Report_005 | C14: Reporting > Spreading tab > Spreading Details | D14: Validate the Spreading Details page. | E14: 1. Log in to the Spreadsmart application. 2. Click Reporting in the page header. 3. Click the Spreading Details sub tab under Spreading tab. | F14: Spreading Details page should have below mentioned components: 1. Group filter dropdown. 2. Model filter dropdown. 3. Analyst Name filter dropdown. 4. Customer Name filter dropdown. 5. Action Date calendar. 6. Spread Status filter dropdown. 7. Spread Type filter dropdown. 8. Format type radio buttons. 9. Information button. 10. Refresh button. 11. Generate Report button. | G14: Pending | I14: Done
B15: Report_006 | C15: Reporting > Spreading tab > Spreading Details | D15: Validate the data in the group filter dropdown on Spreading Details page. | E15: 1. Click Reporting in the page header. 2. Click Spreading Details. 3. Click Group dropdown filter. | F15: "Select Group" should be the default message on the dropdown filter. Data should be visible as per the groups assigned to logged in user. | G15: Pending | I15: Done
B16: Report_007 | C16: Reporting > Spreading tab > Spreading Details | D16: Validate updating the "Group" name in Filter dropdown and Spreading Details report. | E16: 1. Click Reporting in the page header. 2. Click Spreading Details. 3. Update the name of the group. 4. Validate the group name in the dropdown. | F16: 1. Group name should be updated in the Group drop down. 2. Group name should be updated in the Group column of Spreading report. | G16: Pending | I16: Done
B17: Report_008 | C17: Reporting > Spreading tab > Spreading Details | D17: Validate adding a "Group" in Filter dropdown and Spreading Details report. | E17: 1. Click Reporting in the page header. 2. Click Spreading Details. 3. Addd a group and give the access to logged in user. 4. Validate the group in the dropdown. | F17: 1. Added group should be visible in the Group dropdown list. 2. Added group should be visible in the Group column of Spreading report. | G17: Pending | I17: Done
B18: Report_009 | C18: Reporting > Spreading tab > Spreading Details | D18: Validate deleting a "Group" in Filter dropdown and Spreading Details report. | E18: 1. Click Reporting in the page header. 2. Click Spreading Details. 3. Delete a group having access to logged in user. 4. Validate the group in the dropdown. | F18: 1. Deleted group should not be visible in the Group dropdown list. 2. Deleted group should not be visible in the Group column of Spreading report. | G18: Pending | I18: Done
B19: Report_010 | C19: Reporting > Spreading tab > Spreading Details | D19: Validate the Group dropdown list on updating the access of logged in user to a group and Spreading Details report. | E19: 1. Click Reporting in the page header. 2. Click Spreading Details. 3. Change the access of some groups to the logged in User, give access to one. 4. Remove access from a Group. 5. Validate the list of the group dropdown. | F19: 1. Only groups should be visible in the dropdown list of Group, having access to the logged in user. 2. Only groups should be in Group column of Spreading report, which are having access to the logged in use. | G19: Pending | I19: Done
B20: Report_011 | C20: Reporting > Spreading tab > Spreading Details | D20: Validate the functionality of group dropdown filters on Spreading Details page. | E20: 1. Click Reporting in the page header. 2. Click Spreading Details. 3. Click Group dropdown filter. | F20: 1. It should be single select dropdown filter. 2. Dropdown should have a search bar on top to search the group. 3. Dropdown should have a slider, if the list of the group is long. 4. A cross icon should appear against the selected group to unselect/clear the filter. | G20: Pending | I20: Done
B21: Report_012 | C21: Reporting > Spreading tab > Spreading Details | D21: Validate the data in the Model dropdown filter on Spreading Details page. | E21: 1. Click Reporting in the page header. 2. Click Spreading Details. 3. Click Model dropdown filter. | F21: "Select Model" should be the default message on the dropdown filter. Data should be visible as per the selection of the group. | G21: Pending | I21: Done
... B29: Report_020 | C29: Reporting > Spreading tab > Spreading Details | D29: Validate the data in the Analyst Name dropdown filters on Spreading Details page. | E29: 1. Click Reporting in the page header. 2. Click Spreading Details. 3. Click Analyst Name dropdown filter. | F29: "Select Analyst(s)" should be the default message on the dropdown filter, data should contains the list of all the analysts. | G29: Pending | I29: Done
B30: Report_021 | C30: Reporting > Spreading tab > Spreading Details | D30: Validate newly added Analyst in Analyst Name dropdown filters on Spreading Details page and Spreading Details report. | E30: 1. Click Reporting in the page header. 2. Click Spreading Details. 3. Click Analyst Name dropdown filter. | F30: Newly added Analyst Name should be visible in. 1. Analyst Name dropdown filter. 2. Spreading Analyst column on Spreading Details report. | G30: Pending | I30: Pending | J30: 1
B31: Report_022 | C31: Reporting > Spreading tab > Spreading Details | D31: Validate deleted Analyst in Analyst Name dropdown filters on Spreading Details page and Spreading Details report. | E31: 1. Click Reporting in the page header. 2. Click Spreading Details. 3. Click Analyst Name dropdown filter. | F31: Deleted Analyst Name should not be visible in. 1. Analyst Name dropdown filter. 2. Spreading Analyst column on Spreading Details report. | G31: Pending | I31: Pending | J31: 1
B32: Report_023 | C32: Reporting > Spreading tab > Spreading Details | D32: Validate the functionality of Analyst Name dropdown filters on Spreading Details page. | E32: 1. Click Reporting in the page header. 2. Click Spreading Details. 3. Click Analyst Name dropdown filter. | F32: 1. It should be a Multi select dropdown filter. 2. Dropdown should have a search bar to search the model. 3. Dropdown should have a slider, if the list of the Analyst is long. 4. Selection/un select can be done by checking/unchecking checkbox against all Analyst Names. | G32: Pending | I32: Done
B33: Report_024 | C33: Reporting > Spreading tab > Spreading Details | D33: Validate the data in the Customer Name dropdown filters on Spreading Details page. | E33: 1. Click Reporting in the page header. 2. Click Spreading Details. 3. Click Customer Name dropdown filter. | F33: "Select customer" name should be the default message on the dropdown filter. Data should contains the list of all the customers as per the logged in user. | G33: Pending | I33: Done
B34: Report_025 | C34: Reporting > Spreading tab > Spreading Details | D34: Validate a Customer in Customer Name dropdown filters on Spreading Details page and Spreading Details report on giving access to logged in user. | E34: 1. Click Reporting in the page header. 2. Click Spreading Details. 3. Click Customer Name dropdown filter. | F34: When giving access to logged in user, Customer should be visible in. 1. Customer Name dropdown filter. 2. Customer Name column on Spreading Details report. | G34: Pending | I34: Done
B35: Report_026 | C35: Reporting > Spreading tab > Spreading Details | D35: Validate Customer in Customer Name dropdown filters on Spreading Details page and Spreading Details report on revoking access from logged in user. | E35: 1. Click Reporting in the page header. 2. Click Spreading Details. 3. Click Customer Name dropdown filter. | F35: When revoking access from logged in user, Customer should not be visible in. 1. Customer Name dropdown filter. 2. Customer Name column on Spreading Details report. | G35: Pending | I35: Pending | J35: 1
B36: Report_027 | C36: Reporting > Spreading tab > Spreading Details | D36: Validate the functionality of Customer Name dropdown filters on Spreading Details page. | E36: 1. Click Reporting in the page header. 2. Click Spreading Details. 3. Click Customer Name dropdown filter. | F36: 1. It should be a Multi select dropdown filter. 2. Dropdown should have a search bar to search the customer. 3. Dropdown should have a slider, if the list of the customer is long. 4. Selection/un select can be done by checking/unchecking checkbox against all Customer Names. 5. Complete selection can be de-selected by clicking on "Clear Selection". | G36: Pending | I36: Done
B37: Report_028 | C37: Reporting > Spreading tab > Spreading Details | D37: Validate the "Action Date" calendar on Spreading Details page. | E37: 1. Click Reporting in the page header. 2. Click Spreading Details. 3. Click the Action Date calendar. | F37: Action Date calendar should be clickable. "Action Date Range" should be the default message on the calendar. | G37: Pending | I37: Done
B38: Report_029 | C38: Reporting > Spreading tab > Spreading Details | D38: Validate the functionality of "Action Date" calendar on Spreading Details page. | E38: 1. Click Reporting in the page header. 2. Click Spreading Details. 3. Click the Action Date calendar. | F38: 1. It should be a calendar on which start date and end date range can be selected. 2. The user should be able to re-select the date range. | G38: Pending | I38: Done
B39: Report_030 | C39: Reporting > Spreading tab > Spreading Details | D39: Validate the data in the "Spread status" dropdown filters on Spreading Details page. | E39: 1. Click Reporting in the page header. 2. Click Spreading Details. 3. Click Spread Status dropdown filter. | F39: "Select spread status" should be the default message on the dropdown filter. Data should contains the list of all the status of any spread. 1. Draft. 2. For QC. 3. Hold. 4. Received. 5. Rejected. 6. Spread. | G39: Pending | I39: Done
B40: Report_031 | C40: Reporting > Spreading tab > Spreading Details | D40: Validate the functionality of "Spread status" dropdown filters on Spreading Details page. | E40: 1. Click Reporting in the page header. 2. Click Spreading Details. 3. Click Spread Status dropdown filter. | F40: 1. It should be a Multi select dropdown filter. 2. Dropdown should have a search bar to search the spread status. 3. Dropdown should have status like Draft, For QC, Modified, Received, Rejected, Spread. 4. Selection/un select can be done by checking/unchecking checkbox against all Customer Names. | G40: Pending | I40: Done
B41: Report_032 | C41: Reporting > Spreading tab > Spreading Details | D41: Validate the data in the "Spread type" dropdown filters on Spreading Details page. | E41: 1. Click Reporting in the page header. 2. Click Spreading Details. 3. Click Spread type dropdown filter. | F41: Select spread type should be the default message on the dropdown filter, data should contains the list of all the spread types. 1. Adjusted. 2. Original. 3. Restated. | G41: Pending | I41: Done
B42: Report_033 | C42: Reporting > Spreading tab > Spreading Details | D42: Validate the functionality of "Spread type" dropdown filters on Spreading Details page. | E42: 1. Click Reporting in the page header. 2. Click Spreading Details. 3. Click Spread type dropdown filter. | F42: 1. It should be a Multi select dropdown filter. 2. Dropdown should have a search bar to search the spread type. 3. Selection/un select can be done by checking/unchecking checkbox against all Customer Names. | G42: Pending | I42: Done
B43: Report_034 | C43: Reporting > Spreading tab > Spreading Details | D43: Validate the Radio buttons on Spreading Details page. | E43: 1. Click Reporting in the page header. 2. Click Spreading Details. 3. Select any export format radio button. | F43: The export format selector should allow only one option to be selected at a time: 1. Excel 2. PDF 3. HTML | G43: Pending | I43: Done
B44: Report_035 | C44: Reporting > Spreading tab > Spreading Details | D44: Validate the "Information" button on Spreading Details page. | E44: 1. Click Reporting in the page header. 2. Click Spreading Details. 3. Click the Information button. | F44: 1. The Information button should be clickable. 2. Clicking the Information button should open a pop-up message. 3. The pop-up should include a Close button. | G44: Pending | I44: Done
B45: Report_036 | C45: Reporting > Spreading tab > Spreading Details | D45: Validate the "Refresh" button on Spreading Details page. | E45: 1. Click Reporting in the page header. 2. Click Spreading Details. 3. Click the Refresh button. | F45: 1. The Refresh button should be clickable. 2. Clicking Refresh should clear all selected filters. | G45: Pending | I45: Done
B46: Report_037 | C46: Reporting > Spreading tab > Spreading Details | D46: Validate the "Refresh" button on Customer Details page. | E46: 1. Click Reporting in the page header. 2. Click Customer Details. 3. Select any Group and model. 4. Click Refresh button. 5. Click model dropdown. | F46: Model list should not appear until user selects any group. | G46: Pending | H46: 138762 | I46: Pending
B47: Report_038 | C47: Reporting > Spreading tab > Spreading Details | D47: Validate the "Generate Report" button on Spreading Details page. | E47: 1. Click Reporting in the page header. 2. Click Spreading Details. 3. Click the Generate Report button. | F47: 1. The Generate Report button should be clickable. 2. Clicking Generate Report should generate the report in the selected format. | G47: Pending | I47: Done
B48: Report_039 | C48: Reporting > Spreading tab > Spreading Details | D48: Validate "Spreading Details" report without making any selection in the filters. | E48: 1. Click Reporting in the page header. 2. Click Generate report. | F48: Spreading Details report should be generated with the below mentioned columns: Sr. No. Customer Name. Access Group. Statement Date. Spread Type. Frequency. Period. Audit Method. Spreading Analyst(m). Received Date(m). Action Date/Time(M) HH:MM:SS. Machine time(M). User time(M). Spread Time(M). Validation Analyst (C). Received Date (C). Action Date (C). Machine time(C). User time(C). Spread Time(C). | G48: Pending | I48: Done
B49: Report_040 | C49: Reporting > Spreading tab > Spreading Details | D49: Validate "Spreading Details" report without making any selection in the filters. | E49: 1. Click Reporting in the page header. 2. Click Generate report. | F49: Action Date/Time(M), Machine time(M), User time(M), Active time(M), Machine time(C), User time(C), Active time(C), Spread Time(C) and Total time should appear in HH:MM:SS format. | G49: Pending | I49: Pending
B50: Report_041 | C50: Reporting > Spreading tab > Spreading Details | D50: Verify the maker details in the report. | E50: 1. Logged in as a maker. 2. Add an item. 3. Spread it and mapped some values. 4. Submit the spread. | F50: Maker Columns should not appear blank and appropriate data should appear in following columns: Statement Date- Selected Statement Date at the time of submitting the item and appropriate system time. Received Date(M) - Item added date. Action Date/Time(M) HH:MM:SS- Spread date and time. | G50: Pending | I50: Pending
B51: Report_042 | C51: Reporting > Spreading tab > Spreading Details | D51: Verify the checker details in the report. | E51: 1. Logged in as a maker. 2. Add an item. 3. Spread it and mapped some values. 4. Submit the spread for QC. 5. Logged in as a checker. 6. Reject/Submit the spread. | F51: Checker Columns should not appear blank and appropriate data should appear in following columns: Validation Analyst (C)- ID of checker. Received Date (C) - dat of Item submitted for QC. Action Date (C)- Date when checker performed any action. | G51: Pending | I51: Pending
B52: Report_043 | C52: Reporting > Spreading tab > Spreading Details | D52: Verify the maker details in the report. | E52: 1. Logged in as a maker. Scenario-1. If machine time is 1 minutes and. If Maker Started the spreads and worked for 5 minutes then saved as draft then. Machine time =1 Minutes. User time =5 Minutes. Active time = 5 Minutes. Spread time =1+5=6 Minutes. | F52: System should show User time, which will include active session time and total time spent by user on any spreads. | G52: Pending | I52: Pending
B53: Report_044 | C53: Reporting > Spreading tab > Spreading Details | D53: Verify the maker details in the report. | E53: Scenario-2. If machine time is 1 minutes and. If Maker Started the spreads and submitted spreads after 10 Minutes. However, they have spent 5 minutes on Spreading screen and another 5 minutes on research or other activity then. Machine time =1 Minutes. User time =10 Minutes. Active time = 5 Minutes. Spread time=1+10=11 minutes. | F53: System should show the appropriate time. | G53: Pending | I53: Pending
B54: Report_045 | C54: Reporting > Spreading tab > Spreading Details | D54: Verify the checker details in the report. | E54: Scenario-3. I) If machine time is 1 minutes and. Ii) If Maker Started the spreads and submitted spreads for QC after 10 Minutes. However, they have spent 5 minutes on Spreading screen and another 5 minutes on research or other activity. Iii) After rejection from Checker, Maker again spent 10 minutes on Spreading screen without any inactive session, then. Machine time =2 Minutes. User time =20 Minutes. Active time = 15 Minutes. Spread time=2+20=22 minutes. Checker time=10 minutes. Total spreads time=22+10=32. | F54: System should show the appropriate time for checker. | G54: Pending | I54: Pending
B55: Report_046 | C55: Reporting > Spreading tab > Spreading Details | D55: Verify the total time in the report. | E55: Add a customer and add the item. Spread the item and submit it for QC. Login with checker and spread it and then reject the spread. Login again with the maker. Click reporting (Spreading Details). Select the details. Generate the report. | F55: Show Total transaction time in last to show total of maker and checker time (Total Maker time (Machine time+ User time)+Total Checker Time(Machine time+ User time)). | G55: Pending | I55: Pending
B56: Report_047 | C56: Reporting > Spreading tab > Spreading Details | D56: Validate "Spreading Details" report after selecting all the filters. | E56: 1. Click reporting on the page header. 2. Select all required filters. 3. Click Generate Report. | F56: The Spreading Details report should be generated based on the selected filters. | G56: Pending | I56: Done
B57: Report_048 | C57: Reporting > Spreading tab > Spreading Details | D57: Validate "Spreading Details" report after selecting a combination of filters. 1. Group. 2. Analyst Name. | E57: 1. Click Reporting in the page header. 2. Select the required filters. 3. Click Generate Report. | F57: The Spreading Details report should be generated based on the selected filters. | G57: Pending | I57: Pending | J57: 1
B58: Report_049 | C58: Reporting > Spreading tab > Spreading Details | D58: Validate "Spreading Details" report after selecting a combination of filters. 1. Group. 2. Customer Name. | E58: 1. Reporting on the page header. 2. Select the required filters. 3. Click Generate Report. | F58: The Spreading Details report should be generated based on the selected filters. | G58: Pending | I58: Pending | J58: 1
B59: Report_050 | C59: Reporting > Spreading tab > Spreading Details | D59: Validate "Spreading Details" report after selecting a combination of filters. 1. Group. 2. Model. 3. Action Date. | E59: 1. Reporting on the page header. 2. Select the required filters. 3. Click Generate Report. | F59: The Spreading Details report should be generated based on the selected filters. | G59: Pending | I59: Pending | J59: 1
B60: Report_051 | C60: Reporting > Spreading tab > Spreading Details | D60: Validate "Spreading Details" report after selecting a combination of filters. 1. Spread status. 2. Spread type. | E60: 1. Reporting on the page header. 2. Select the required filters. 3. Click Generate Report. | F60: The Spreading Details report should be generated based on the selected filters. | G60: Pending | I60: Pending | J60: 1
B61: Report_052 | C61: Reporting > Spreading tab > Spreading Details | D61: Validate "Spreading Details" report after selecting a combination of filters. 1. Spread status. 2. Spread type. 3. Customer Name. | E61: 1. Reporting on the page header. 2. Select the required filters. 3. Click Generate Report. | F61: The Spreading Details report should be generated based on the selected filters. | G61: Pending | I61: Pending | J61: 1
B62: Report_053 | C62: Reporting > Spreading tab > Spreading Details | D62: Validate the "Spreading Details" report in "Excel" format. | E62: 1. Log in to the Spreadsmart application. 2. Click Reporting in the page header. 3. Select the Excel format radio button. 4. Click Generate Report. | F62: The report should be generated in Excel format. | G62: Pending | I62: Done
B63: Report_054 | C63: Reporting > Spreading tab > Spreading Details | D63: Validate the "Spreading Details" report in "PDF" format. | E63: 1. Log in to the Spreadsmart application. 2. Click Reporting in the page header. 3. Select the PDF format radio button. 4. Click Generate Report. | F63: The report should be generated in PDF format. | G63: Pending | I63: Done
B64: Report_055 | C64: Reporting > Spreading tab > Spreading Details | D64: Validate the "Spreading Details" report in "HTML" format. | E64: 1. Log in to the Spreadsmart application. 2. Click Reporting in the page header. 3. Select the HTML format radio button. 4. Click Generate Report. | F64: The report should be generated in HTML format. | G64: Pending | I64: Done
B65: Report_056 | C65: Reporting > Spreading tab > Spreading Details | D65: Validate the data in the Spreading Details report on updating the values like. 1. Spread Status. 2. Spread Type. 3. Frequency. 4. Audit Method. 5. Action Date. 6. Received Date. | E65: Update all the Values and then click. 1. Reporting on the page header. 2. Select the required filters. 3. Click Generate Report. | F65: Data should be modified and should be visible in the Spreading Details report. | G65: Pending | I65: Pending | J65: 1
B66: Report_057 | C66: Reporting > Spreading tab > Customer Details | D66: Validate the Customer Details page. | E66: 1. Log in to the Spreadsmart application. 2. Click Reporting in the page header. 3. Click the Customer Details under Spreading. | F66: Customer Details page should have below mentioned components: 1. Group dropdowns filter. 2. Model filer dropdowns. 3. Status filter dropdowns. 4. Format type radio buttons. 5. Information button. 6. Refresh button. 7. Generate Report button. | G66: Pending | I66: Done
